Workbook

Sheet README_Fundos
B2: Extensão de nível FUNDO — abas para adicionar à planilha de deals
B3: Termos extraídos de 3 pacotes sintéticos de documentos de fundo. Estrutura de referência: ILPA Model LPA e ILPA Principles 3.0.
B5: O que fazer com este arquivo | C5: Copie as abas Funds, Fund_Terms, Side_Letters, Obligations, Dicionario_Termos_Fundos e Stats_Fundos para dentro da planilha existente de deals. As abas de deal (Deals, Terms, Dicionario_Termos, Pendente, Publicado, Templates) não precisam ser alteradas — exceto pela única mudança descrita na linha seguinte.
B6: ÚNICA alteração nas abas existentes | C6: Adicionar uma coluna 'Nivel' às abas Deals e Terms, com valor fixo 'deal' em todas as linhas. Isso permite que consultas e o dashboard filtrem entre os dois níveis sem ambiguidade. Sem essa coluna, uma contagem de 'quantos têm MFN' mistura side letter de LP com side letter de investidor em SAFE.
B7: Coluna Camada (a decisão de triagem) | C7: 1 = vai para o dashboard (varia entre fundos + é consultado com frequência + é acionável). 2 = fica na planilha, consultável em linguagem natural, fora da tela. 3 = ponteiro apenas — o agente registra onde está a cláusula e não extrai valor, porque o termo é funcionalmente invariante entre fundos.
B8: Coluna Escopo | C8: gestora / fundo / veiculo / LP. Termos de escopo 'gestora' aparecem uma única vez, não repetidos por fundo — evita quatro linhas idênticas.
B9: Referência ILPA vs. padrão de mercado | C9: A coluna 'Referência ILPA' traz a posição do ILPA Model LPA / Principles 3.0, que é declaradamente LP-friendly — não é a prática mediana de mercado. Desviar do ILPA é comum e não é por si um sinal ruim. Ler 'Desvio vs ILPA' como direção, não como nota.
B10: Aba Obligations | C10: Estado derivado, não termo extraído. Recalcula com o relógio, não com assinatura de documento. Ciclo de atualização e semântica de falha diferentes: célula vazia aqui NÃO significa 'nada vence' — significa 'não calculado'. As duas condições têm status distintos na coluna Status_Calculo.
B11: Fonte normativa | C11: ILPA Model LPA (Whole-of-Fund, out/2019, atualizado jul/2020; Deal-by-Deal, jul/2020), Delaware-law based; ILPA Principles 3.0 (jun/2019). Numeração de seção dos documentos sintéticos segue o esqueleto do Model LPA onde aplicável. https://ilpa.org/industry-guidance/templates-standards-model-documents/
B12: Status dos dados | C12: SINTÉTICO. Alqueire Ventures, os LPs, as DFIs e todos os valores são fictícios. Serve como fixture para testar o agente de extração antes de haver acesso a documentos reais.

Sheet Funds
A1: Fund ID | B1: Nivel | C1: Fundo | D1: Vintage | E1: Jurisdição / Forma legal | F1: Veículos paralelos e feeders | G1: Aggregate Commitments (USD) | H1: Fim do Período de Investimento | I1: Fim do Prazo | J1: Waterfall | K1: Nº de LPs com side letter | L1: Source Package
A2: F1 | B2: fundo | C2: Alqueire Ventures Fund I, L.P. | D2: 2019 | E2: Cayman Islands exempted LP | F2: Nenhum | G2: 45000000 | H2: 14/06/2023 (4 anos, extensível 1 ano a critério do GP) | I2: 10 anos do Final Closing + 2 x 1 ano com consentimento do LPAC | J2: Deal-by-deal | K2: 1 | L2: 01_Alqueire Ventures Fund I
A3: F3 | B3: fundo | C3: Alqueire Ventures Fund III, L.P. | D3: 2023 | E3: Cayman Islands exempted LP + FIP feeder (CVM 175) | F3: Alqueire Ventures III FIP Multiestratégia (US$37,5M) | G3: 180000000 | H3: 28/04/2028 (5 anos, extensível 1 ano com consentimento do LPAC) | I3: 10 anos do Final Closing + 2 x 1 ano com maioria dos LPs | J3: Whole-of-fund | K3: 3 | L3: 02_Alqueire Ventures Fund III
A4: F4 | B4: fundo | C4: Alqueire Ventures Fund IV, L.P. | D4: 2026 | E4: Cayman exempted LP + Delaware parallel + FIP feeder | F4: Alqueire Ventures Fund IV (US), L.P. (US$61M); Alqueire Ventures IV FIP Multiestratégia (US$45M) | G4: 320000000 | H4: 19/02/2031 (5 anos, extensível 1 ano com consentimento do LPAC) | I4: 12 anos do Final Closing + 2 x 1 ano com maioria dos LPs | J4: Whole-of-fund + tier interino | K4: 4 | L4: 03_Alqueire Ventures Fund IV

Sheet Fund_Terms
A1: Term ID | B1: Camada | C1: Nivel | D1: Escopo | E1: Fund ID | F1: Fundo | G1: Categoria | H1: Termo Canônico | I1: Valor Extraído | J1: Documento Fonte | K1: Seção Fonte | L1: Referência ILPA | M1: Desvio vs ILPA | N1: Nota | O1: Confiança
A2: FT-001 | B2: 1 | C2: fundo | D2: fundo | E2: F1 | F2: Alqueire Ventures Fund I, L.P. | G2: Eixo | H2: Jurisdição e forma legal | I2: Cayman Islands exempted LP; sem veículo paralelo | J2: 1 - A&R Exempted Limited Partnership Agreement | K2: Preâmbulo | L2: — | M2: n/a | O2: High Confidence
A3: FT-002 | B3: 1 | C3: fundo | D3: fundo | E3: F3 | F3: Alqueire Ventures Fund III, L.P. | G3: Eixo | H3: Jurisdição e forma legal | I3: Cayman exempted LP + FIP feeder brasileiro (CVM 175) | J3: 1 - Exempted Limited Partnership Agreement | K3: 1.1 def. Feeder Fund; 15.5 | L3: — | M3: n/a | O3: High Confidence
A4: FT-003 | B4: 1 | C4: fundo | D4: fundo | E4: F4 | F4: Alqueire Ventures Fund IV, L.P. | G4: Eixo | H4: Jurisdição e forma legal | I4: Cayman exempted LP + Delaware parallel + FIP feeder | J4: 1 - Exempted Limited Partnership Agreement | K4: 1.1 def. Delaware Parallel Fund / Feeder Fund | L4: — | M4: n/a | O4: High Confidence
A5: FT-004 | B5: 1 | C5: fundo | D5: fundo | E5: F1 | F5: Alqueire Ventures Fund I, L.P. | G5: Eixo | H5: Aggregate Commitments (final close) | I5: US$45.000.000 | J5: 1 - A&R Exempted Limited Partnership Agreement | K5: 1.1 def. Aggregate Commitments | L5: — | M5: n/a | O5: High Confidence
A6: FT-005 | B6: 1 | C6: fundo | D6: fundo | E6: F3 | F6: Alqueire Ventures Fund III, L.P. | G6: Eixo | H6: Aggregate Commitments (final close) | I6: US$180.000.000 (US$142,5M Partnership + US$37,5M Feeder) | J6: 1 - Exempted Limited Partnership Agreement | K6: 1.1 def. Aggregate Commitments | L6: — | M6: n/a | O6: High Confidence
A7: FT-006 | B7: 1 | C7: fundo | D7: fundo | E7: F4 | F7: Alqueire Ventures Fund IV, L.P. | G7: Eixo | H7: Aggregate Commitments (final close) | I7: US$320.000.000 (US$214M + US$61M Delaware + US$45M Feeder) | J7: 1 - Exempted Limited Partnership Agreement | K7: 1.1 def. Aggregate Commitments | L7: — | M7: n/a | O7: High Confidence
A8: FT-007 | B8: 1 | C8: fundo | D8: fundo | E8: F1 | F8: Alqueire Ventures Fund I, L.P. | G8: Eixo | H8: Fim do período de investimento | I8: 4 anos do Initial Closing; extensível 1 ano a exclusivo critério do GP | J8: 1 - A&R Exempted Limited Partnership Agreement | K8: 1.1 def. Commitment Period | L8: — | M8: Sim | N8: Extensão sem consentimento de LP nem do LPAC | O8: Review
A9: FT-008 | B9: 1 | C9: fundo | D9: fundo | E9: F3 | F9: Alqueire Ventures Fund III, L.P. | G9: Eixo | H9: Fim do período de investimento | I9: 5 anos; extensível 1 ano com consentimento do LPAC | J9: 1 - Exempted Limited Partnership Agreement | K9: 1.1 def. Commitment Period | L9: — | M9: Não | O9: High Confidence
A10: FT-009 | B10: 1 | C10: fundo | D10: fundo | E10: F4 | F10: Alqueire Ventures Fund IV, L.P. | G10: Eixo | H10: Fim do período de investimento | I10: 5 anos; extensível 1 ano com consentimento do LPAC | J10: 1 - Exempted Limited Partnership Agreement | K10: 1.1 def. Commitment Period | L10: — | M10: Não | O10: High Confidence
A11: FT-010 | B11: 1 | C11: fundo | D11: fundo | E11: F1 | F11: Alqueire Ventures Fund I, L.P. | G11: Eixo | H11: Fim do prazo e extensões | I11: 10 anos do Final Closing + 2 x 1 ano com consentimento do LPAC | J11: 1 - A&R Exempted Limited Partnership Agreement | K11: 1.1 def. Term | L11: — | M11: Não | O11: High Confidence
A12: FT-011 | B12: 1 | C12: fundo | D12: fundo | E12: F3 | F12: Alqueire Ventures Fund III, L.P. | G12: Eixo | H12: Fim do prazo e extensões | I12: 10 anos + 2 x 1 ano com maioria dos LPs | J12: 1 - Exempted Limited Partnership Agreement | K12: 1.1 def. Term | L12: — | M12: Não | O12: High Confidence
A13: FT-012 | B13: 1 | C13: fundo | D13: fundo | E13: F4 | F13: Alqueire Ventures Fund IV, L.P. | G13: Eixo | H13: Fim do prazo e extensões | I13: 12 anos + 2 x 1 ano com maioria dos LPs | J13: 1 - Exempted Limited Partnership Agreement | K13: 1.1 def. Term | L13: — | M13: Não | N13: Prazo mais longo, consistente com VC | O13: High Confidence
A14: FT-013 | B14: 1 | C14: fundo | D14: fundo | E14: F1 | F14: Alqueire Ventures Fund I, L.P. | G14: Economia | H14: Management fee — percentual e base | I14: 2,50% a.a. de Aggregate Commitments | J14: 1 - A&R Exempted Limited Partnership Agreement | K14: 4.1 | L14: Sem posição de taxa; base deve ser transparente | M14: n/a | O14: High Confidence
A15: FT-014 | B15: 1 | C15: fundo | D15: fundo | E15: F3 | F15: Alqueire Ventures Fund III, L.P. | G15: Economia | H15: Management fee — percentual e base | I15: 2,00% a.a. de Aggregate Commitments | J15: 1 - Exempted Limited Partnership Agreement | K15: 4.1 | L15: Sem posição de taxa; base deve ser transparente | M15: n/a | O15: High Confidence
A16: FT-015 | B16: 1 | C16: fundo | D16: fundo | E16: F4 | F16: Alqueire Ventures Fund IV, L.P. | G16: Economia | H16: Management fee — percentual e base | I16: 2,00% a.a. de Aggregate Commitments | J16: 1 - Exempted Limited Partnership Agreement | K16: 4.1 | L16: Sem posição de taxa; base deve ser transparente | M16: n/a | O16: High Confidence
A17: FT-016 | B17: 1 | C17: fundo | D17: fundo | E17: F1 | F17: Alqueire Ventures Fund I, L.P. | G17: Economia | H17: Step-down — percentual, base e data | I17: NÃO HÁ. Fee permanece sobre Aggregate Commitments por todo o Term | J17: 1 - A&R Exempted Limited Partnership Agreement | K17: 4.2 | L17: Redução deve considerar realizações e write-downs | M17: Sim | N17: Ausência de step-down é o desvio econômico mais material do Fundo I | O17: Review
A18: FT-017 | B18: 1 | C18: fundo | D18: fundo | E18: F3 | F18: Alqueire Ventures Fund III, L.P. | G18: Economia | H18: Step-down — percentual, base e data | I18: 1,50% a.a. de Invested Cost, líquido de realizações e write-downs, a partir do earlier de fim do período de investimento e initial close do fundo sucessor | J18: 1 - Exempted Limited Partnership Agreement | K18: 4.2; 1.1 def. Invested Cost | L18: Redução deve considerar realizações e write-downs | M18: Não | N18: Alinhado à atualização de jul/2020 do Model LPA | O18: High Confidence
A19: FT-018 | B19: 1 | C19: fundo | D19: fundo | E19: F4 | F19: Alqueire Ventures Fund IV, L.P. | G19: Economia | H19: Step-down — percentual, base e data | I19: 1,25% a.a. de Invested Cost, líquido de realizações e write-downs | J19: 1 - Exempted Limited Partnership Agreement | K19: 4.2 | L19: Redução deve considerar realizações e write-downs | M19: Não | O19: High Confidence
A20: FT-019 | B20: 1 | C20: fundo | D20: fundo | E20: F1 | F20: Alqueire Ventures Fund I, L.P. | G20: Economia | H20: Offset de fees de portfolio | I20: 50% do valor recebido; saldo retido pelo Manager | J20: 1 - A&R Exempted Limited Partnership Agreement | K20: 4.3 | L20: 100% de offset | M20: Sim | O20: Review
A21: FT-020 | B21: 1 | C21: fundo | D21: fundo | E21: F3 | F21: Alqueire Ventures Fund III, L.P. | G21: Economia | H21: Offset de fees de portfolio | I21: 100%, com excedente carregado para trimestres futuros | J21: 1 - Exempted Limited Partnership Agreement | K21: 4.3 | L21: 100% de offset | M21: Não | O21: High Confidence
A22: FT-021 | B22: 1 | C22: fundo | D22: fundo | E22: F4 | F22: Alqueire Ventures Fund IV, L.P. | G22: Economia | H22: Offset de fees de portfolio | I22: 100%, com excedente carregado | J22: 1 - Exempted Limited Partnership Agreement | K22: 4.3 | L22: 100% de offset | M22: Não | O22: High Confidence
A23: FT-022 | B23: 1 | C23: fundo | D23: fundo | E23: F1 | F23: Alqueire Ventures Fund I, L.P. | G23: Economia | H23: Tipo de waterfall | I23: Deal-by-deal (Portfolio Investment-by-Portfolio Investment) | J23: 1 - A&R Exempted Limited Partnership Agreement | K23: 8.2 | L23: Whole-of-fund | M23: Sim | N23: ILPA prefere whole-of-fund para limitar risco de clawback | O23: Review
A24: FT-023 | B24: 1 | C24: fundo | D24: fundo | E24: F3 | F24: Alqueire Ventures Fund III, L.P. | G24: Economia | H24: Tipo de waterfall | I24: Whole-of-fund | J24: 1 - Exempted Limited Partnership Agreement | K24: 8.1 | L24: Whole-of-fund | M24: Não | O24: High Confidence
A25: FT-024 | B25: 1 | C25: fundo | D25: fundo | E25: F4 | F25: Alqueire Ventures Fund IV, L.P. | G25: Economia | H25: Tipo de waterfall | I25: Whole-of-fund, com tier interino discricionário após 5 anos (art. 8.3) | J25: 1 - Exempted Limited Partnership Agreement | K25: 8.1; 8.3 | L25: Whole-of-fund | M25: Parcial | N25: Tier interino é desvio, mas mitigado por escrow de 100% sobre o valor antecipado | O25: High Confidence
A26: FT-025 | B26: 1 | C26: fundo | D26: fundo | E26: F1 | F26: Alqueire Ventures Fund I, L.P. | G26: Economia | H26: Preferred return — percentual | I26: 8% a.a., capitalizado anualmente | J26: 1 - A&R Exempted Limited Partnership Agreement | K26: 1.1 def. Preferred Return | L26: Deve acumular até devolução integral do capital | M26: Não | O26: High Confidence
A27: FT-026 | B27: 1 | C27: fundo | D27: fundo | E27: F3 | F27: Alqueire Ventures Fund III, L.P. | G27: Economia | H27: Preferred return — percentual | I27: 8% a.a., capitalizado anualmente; acumula até devolução integral | J27: 1 - Exempted Limited Partnership Agreement | K27: 1.1 def. Preferred Return | L27: Deve acumular até devolução integral do capital | M27: Não | O27: High Confidence
A28: FT-027 | B28: 1 | C28: fundo | D28: fundo | E28: F4 | F28: Alqueire Ventures Fund IV, L.P. | G28: Economia | H28: Preferred return — percentual | I28: 8% a.a., capitalizado anualmente; acumula até devolução integral | J28: 1 - Exempted Limited Partnership Agreement | K28: 1.1 def. Preferred Return | L28: Deve acumular até devolução integral do capital | M28: Não | O28: High Confidence
A29: FT-028 | B29: 1 | C29: fundo | D29: fundo | E29: F1 | F29: Alqueire Ventures Fund I, L.P. | G29: Economia | H29: Carried interest — percentual | I29: 20% | J29: 1 - A&R Exempted Limited Partnership Agreement | K29: 1.1 def. Carried Interest; 8.2(d) | L29: — | M29: n/a | O29: High Confidence
A30: FT-029 | B30: 1 | C30: fundo | D30: fundo | E30: F3 | F30: Alqueire Ventures Fund III, L.P. | G30: Economia | H30: Carried interest — percentual | I30: 20% | J30: 1 - Exempted Limited Partnership Agreement | K30: 8.1(d) | L30: — | M30: n/a | O30: High Confidence
A31: FT-030 | B31: 1 | C31: fundo | D31: fundo | E31: F4 | F31: Alqueire Ventures Fund IV, L.P. | G31: Economia | H31: Carried interest — percentual | I31: DUAS CLASSES: 20% (Class A) e 17,5% (Class B — Development Finance Investors) | J31: 1 - Exempted Limited Partnership Agreement | K31: 1.1 def. Class A/B Interest; 8.2 | L31: — | M31: n/a | N31: Cálculo separado por classe; Class A não absorve a redução da Class B | O31: High Confidence
A32: FT-031 | B32: 1 | C32: fundo | D32: fundo | E32: F1 | F32: Alqueire Ventures Fund I, L.P. | G32: Economia | H32: GP catch-up — percentual | I32: 100% ao GP até atingir 20% | J32: 1 - A&R Exempted Limited Partnership Agreement | K32: 8.2(c) | L32: — | M32: Sim | N32: Catch-up integral é agressivo | O32: Review
A33: FT-032 | B33: 1 | C33: fundo | D33: fundo | E33: F3 | F33: Alqueire Ventures Fund III, L.P. | G33: Economia | H33: GP catch-up — percentual | I33: 50/50 | J33: 1 - Exempted Limited Partnership Agreement | K33: 8.1(c) | L33: — | M33: Não | O33: High Confidence
A34: FT-033 | B34: 1 | C34: fundo | D34: fundo | E34: F4 | F34: Alqueire Ventures Fund IV, L.P. | G34: Economia | H34: GP catch-up — percentual | I34: 50/50 | J34: 1 - Exempted Limited Partnership Agreement | K34: 8.1(c) | L34: — | M34: Não | O34: High Confidence
A35: FT-034 | B35: 1 | C35: fundo | D35: fundo | E35: F1 | F35: Alqueire Ventures Fund I, L.P. | G35: Economia | H35: Carry escrow — percentual retido | I35: NENHUM | J35: 1 - A&R Exempted Limited Partnership Agreement | K35: 8.4 | L35: 30% das distribuições de carry | M35: Sim | N35: Combinado com clawback sem garantia, é o maior risco econômico do Fundo I | O35: Review
A36: FT-035 | B36: 1 | C36: fundo | D36: fundo | E36: F3 | F36: Alqueire Ventures Fund III, L.P. | G36: Economia | H36: Carry escrow — percentual retido | I36: 30% | J36: 1 - Exempted Limited Partnership Agreement | K36: 8.2 | L36: 30% das distribuições de carry | M36: Não | N36: Igual à referência do Principles 3.0 | O36: High Confidence
A37: FT-036 | B37: 1 | C37: fundo | D37: fundo | E37: F4 | F37: Alqueire Ventures Fund IV, L.P. | G37: Economia | H37: Carry escrow — percentual retido | I37: 30%; e 100% sobre qualquer distribuição feita sob o tier interino do art. 8.3 | J37: 1 - Exempted Limited Partnership Agreement | K37: 8.4 | L37: 30% das distribuições de carry | M37: Não | O37: High Confidence
A38: FT-037 | B38: 1 | C38: fundo | D38: fundo | E38: F1 | F38: Alqueire Ventures Fund I, L.P. | G38: Economia | H38: Clawback — tipo de garantia | I38: SEM GARANTIA. Sem escrow e sem garantia pessoal. Cálculo líquido de impostos pagos | J38: 1 - A&R Exempted Limited Partnership Agreement | K38: 8.3; 8.4 | L38: Escrow + garantia pessoal dos beneficiários finais, opcionalmente solidária | M38: Sim | N38: Obrigação de clawback existe mas é economicamente desprotegida | O38: Review
A39: FT-038 | B39: 1 | C39: fundo | D39: fundo | E39: F3 | F39: Alqueire Ventures Fund III, L.P. | G39: Economia | H39: Clawback — tipo de garantia | I39: Escrow de 30% + garantias pessoais SEVERAIS (não solidárias), limitadas ao carry efetivamente recebido por cada beneficiário | J39: 1 - Exempted Limited Partnership Agreement | K39: 8.3; 8.4 | L39: Escrow + garantia pessoal dos beneficiários finais, opcionalmente solidária | M39: Parcial | N39: ILPA admite base solidária como opção; aqui é apenas several | O39: High Confidence
A40: FT-039 | B40: 1 | C40: fundo | D40: fundo | E40: F4 | F40: Alqueire Ventures Fund IV, L.P. | G40: Economia | H40: Clawback — tipo de garantia | I40: Escrow de 30% + garantias pessoais SOLIDÁRIAS (joint and several), com certificado anual ao LPAC confirmando vigência e suficiência patrimonial | J40: 1 - Exempted Limited Partnership Agreement | K40: 8.5; 8.6 | L40: Escrow + garantia pessoal dos beneficiários finais, opcionalmente solidária | M40: Não | N40: Certificado anual é proteção acima da referência ILPA | O40: High Confidence
A41: FT-040 | B41: 1 | C41: fundo | D41: fundo | E41: F1 | F41: Alqueire Ventures Fund I, L.P. | G41: Economia | H41: Recycling — permitido e limite | I41: Permitido durante o período de investimento, SEM LIMITE de valor | J41: 1 - A&R Exempted Limited Partnership Agreement | K41: 8.5 | L41: — | M41: Sim | O41: Review
A42: FT-041 | B42: 1 | C42: fundo | D42: fundo | E42: F3 | F42: Alqueire Ventures Fund III, L.P. | G42: Economia | H42: Recycling — permitido e limite | I42: Até 120% de Aggregate Commitments; vedado após 2 anos do fim do período de investimento | J42: 1 - Exempted Limited Partnership Agreement | K42: 8.5 | L42: — | M42: Não | O42: High Confidence
A43: FT-042 | B43: 1 | C43: fundo | D43: fundo | E43: F4 | F43: Alqueire Ventures Fund IV, L.P. | G43: Economia | H43: Recycling — permitido e limite | I43: Até 115% de Aggregate Commitments; vedado após 2 anos do fim do período de investimento | J43: 1 - Exempted Limited Partnership Agreement | K43: 8.7 | L43: — | M43: Não | O43: High Confidence
A44: FT-043 | B44: 1 | C44: fundo | D44: fundo | E44: F1 | F44: Alqueire Ventures Fund I, L.P. | G44: Economia | H44: GP commitment — percentual | I44: 1,0%; integralmente satisfazível por waiver de management fee | J44: 1 - A&R Exempted Limited Partnership Agreement | K44: 5.1 | L44: — | M44: Sim | N44: Waiver integral esvazia o alinhamento | O44: Review
A45: FT-044 | B45: 1 | C45: fundo | D45: fundo | E45: F3 | F45: Alqueire Ventures Fund III, L.P. | G45: Economia | H45: GP commitment — percentual | I45: 2,0%; no mínimo metade em caixa; no máximo 50% por waiver de fee | J45: 1 - Exempted Limited Partnership Agreement | K45: 5.1 | L45: — | M45: Não | O45: High Confidence
A46: FT-045 | B46: 1 | C46: fundo | D46: fundo | E46: F4 | F46: Alqueire Ventures Fund IV, L.P. | G46: Economia | H46: GP commitment — percentual | I46: 2,5%; no mínimo 60% em caixa; no máximo 40% por waiver de fee | J46: 1 - Exempted Limited Partnership Agreement | K46: 5.1 | L46: — | M46: Não | O46: High Confidence
A47: FT-046 | B47: 1 | C47: fundo | D47: fundo | E47: F1 | F47: Alqueire Ventures Fund I, L.P. | G47: Quórum | H47: No-fault removal — quórum e haircut | I47: 80% de Aggregate Commitments; SEM haircut no carry; GP recebe fee por 12 meses após remoção | J47: 1 - A&R Exempted Limited Partnership Agreement | K47: 11.3 | L47: Previsto, sem pagamento de fee adicional; opção de haircut por supermaioria | M47: Sim | N47: Quórum alto + fee pós-remoção + zero haircut: remoção economicamente inviável | O47: Review
A48: FT-047 | B48: 1 | C48: fundo | D48: fundo | E48: F3 | F48: Alqueire Ventures Fund III, L.P. | G48: Quórum | H48: No-fault removal — quórum e haircut | I48: 66⅔%; sem fee após remoção; haircut de 25% no carry por voto de supermaioria de 2/3 | J48: 1 - Exempted Limited Partnership Agreement | K48: 11.4 | L48: Previsto, sem pagamento de fee adicional; opção de haircut por supermaioria | M48: Não | O48: High Confidence
A49: FT-048 | B49: 1 | C49: fundo | D49: fundo | E49: F4 | F49: Alqueire Ventures Fund IV, L.P. | G49: Quórum | H49: No-fault removal — quórum e haircut | I49: 60%; sem fee após remoção; haircut de 30% no carry | J49: 1 - Exempted Limited Partnership Agreement | K49: 11.4 | L49: Previsto, sem pagamento de fee adicional; opção de haircut por supermaioria | M49: Não | O49: High Confidence
A50: FT-049 | B50: 1 | C50: fundo | D50: fundo | E50: F1 | F50: Alqueire Ventures Fund I, L.P. | G50: Quórum | H50: Removal for cause — quórum e efeito no carry | I50: 66⅔%, exigindo decisão judicial final e irrecorrível; carry reduzido em 50% | J50: 1 - A&R Exempted Limited Partnership Agreement | K50: 11.2 | L50: Redução de 100% do carry | M50: Sim | N50: Exigência de decisão judicial final torna a cláusula quase inoperante | O50: Review
A51: FT-050 | B51: 1 | C51: fundo | D51: fundo | E51: F3 | F51: Alqueire Ventures Fund III, L.P. | G51: Quórum | H51: Removal for cause — quórum e efeito no carry | I51: 50%, admitindo decisão arbitral; carry reduzido em 100% | J51: 1 - Exempted Limited Partnership Agreement | K51: 11.3 | L51: Redução de 100% do carry | M51: Não | O51: High Confidence
A52: FT-051 | B52: 1 | C52: fundo | D52: fundo | E52: F4 | F52: Alqueire Ventures Fund IV, L.P. | G52: Quórum | H52: Removal for cause — quórum e efeito no carry | I52: 50%; inclui como causa finding final de Prohibited Practice por DFI; carry reduzido em 100% | J52: 1 - Exempted Limited Partnership Agreement | K52: 11.3 | L52: Redução de 100% do carry | M52: Não | N52: Gatilho de integridade DFI é adição acima da referência ILPA | O52: High Confidence
A53: FT-052 | B53: 1 | C53: fundo | D53: fundo | E53: F1 | F53: Alqueire Ventures Fund I, L.P. | G53: Quórum | H53: Término antecipado do período de investimento | I53: 75% de Aggregate Commitments | J53: 1 - A&R Exempted Limited Partnership Agreement | K53: 11.4 | L53: Direito do LP a partir de quórum suficiente | M53: Parcial | O53: High Confidence
A54: FT-053 | B54: 1 | C54: fundo | D54: fundo | E54: F3 | F54: Alqueire Ventures Fund III, L.P. | G54: Quórum | H54: Término antecipado do período de investimento | I54: 66⅔%, sem causa, com aviso de 60 dias | J54: 1 - Exempted Limited Partnership Agreement | K54: 11.5 | L54: Direito do LP a partir de quórum suficiente | M54: Não | O54: High Confidence
A55: FT-054 | B55: 1 | C55: fundo | D55: fundo | E55: F4 | F55: Alqueire Ventures Fund IV, L.P. | G55: Quórum | H55: Término antecipado do período de investimento | I55: 60%, sem causa, com aviso de 60 dias | J55: 1 - Exempted Limited Partnership Agreement | K55: 11.5 | L55: Direito do LP a partir de quórum suficiente | M55: Não | O55: High Confidence
A56: FT-055 | B56: 1 | C56: fundo | D56: fundo | E56: F1 | F56: Alqueire Ventures Fund I, L.P. | G56: Quórum | H56: Change of control do GP — quórum | I56: Apenas consentimento do LPAC; NENHUM consentimento de LP exigido | J56: 1 - A&R Exempted Limited Partnership Agreement | K56: 9.4 | L56: Maioria significativa de LPs | M56: Sim | N56: LPAC é nomeado pelo próprio GP, então o consentimento é circular | O56: Review
A57: FT-056 | B57: 1 | C57: fundo | D57: fundo | E57: F3 | F57: Alqueire Ventures Fund III, L.P. | G57: Quórum | H57: Change of control do GP — quórum | I57: 75% de Aggregate Commitments detidos por LPs | J57: 1 - Exempted Limited Partnership Agreement | K57: 9.4 | L57: Maioria significativa de LPs | M57: Não | O57: High Confidence
A58: FT-057 | B58: 1 | C58: fundo | D58: fundo | E58: F4 | F58: Alqueire Ventures Fund IV, L.P. | G58: Quórum | H58: Change of control do GP — quórum | I58: 75% de Aggregate Commitments detidos por LPs | J58: 1 - Exempted Limited Partnership Agreement | K58: 9.4 | L58: Maioria significativa de LPs | M58: Não | O58: High Confidence
A59: FT-058 | B59: 1 | C59: fundo | D59: fundo | E59: F1 | F59: Alqueire Ventures Fund I, L.P. | G59: Quórum | H59: Emendas — quórum | I59: Maioria simples; GP pode emendar unilateralmente em hipóteses amplas | J59: 1 - A&R Exempted Limited Partnership Agreement | K59: 9.5 | L59: — | M59: Sim | O59: Review
A60: FT-059 | B60: 1 | C60: fundo | D60: fundo | E60: F3 | F60: Alqueire Ventures Fund III, L.P. | G60: Quórum | H60: Emendas — quórum | I60: 2/3; consentimento individual de LP desproporcionalmente afetado | J60: 1 - Exempted Limited Partnership Agreement | K60: 9.5 | L60: — | M60: Não | O60: High Confidence
A61: FT-060 | B61: 1 | C61: fundo | D61: fundo | E61: F4 | F61: Alqueire Ventures Fund IV, L.P. | G61: Quórum | H61: Emendas — quórum | I61: 2/3; consentimento individual do afetado; e consentimento de CADA DFI para emendar 2.2(c), 2.3 ou Schedule G | J61: 1 - Exempted Limited Partnership Agreement | K61: 9.5 | L61: — | M61: Não | N61: Veto individual de DFI sobre exclusion list | O61: High Confidence
A62: FT-061 | B62: 1 | C62: fundo | D62: fundo | E62: F1 | F62: Alqueire Ventures Fund I, L.P. | G62: Quórum | H62: Transação com afiliada — LPAC exigido? | I62: NÃO. GP decide sozinho mediante determinação de boa-fé de arm's length; pode ainda PRÉ-LIBERAR categorias de conflito por até 12 meses via disclosure em relatório | J62: 1 - A&R Exempted Limited Partnership Agreement | K62: 9.3 | L62: LPAC aprova todas, mesmo em condições de mercado; sem pre-clearance | M62: Sim | N62: Contraria diretamente duas posições do Model LPA: consentimento do LPAC e vedação de pre-clearance | O62: Review
A63: FT-062 | B63: 1 | C63: fundo | D63: fundo | E63: F3 | F63: Alqueire Ventures Fund III, L.P. | G63: Quórum | H63: Transação com afiliada — LPAC exigido? | I63: SIM, para todas, inclusive as que o GP considere arm's length. Pre-clearance vedado; disclosure em relatório não constitui consentimento | J63: 1 - Exempted Limited Partnership Agreement | K63: 9.3 | L63: LPAC aprova todas, mesmo em condições de mercado; sem pre-clearance | M63: Não | O63: High Confidence
A64: FT-063 | B64: 1 | C64: fundo | D64: fundo | E64: F4 | F64: Alqueire Ventures Fund IV, L.P. | G64: Quórum | H64: Transação com afiliada — LPAC exigido? | I64: SIM, mesma redação do Fundo III | J64: 1 - Exempted Limited Partnership Agreement | K64: 9.3 | L64: LPAC aprova todas, mesmo em condições de mercado; sem pre-clearance | M64: Não | O64: High Confidence
A65: FT-064 | B65: 1 | C65: fundo | D65: fundo | E65: F1 | F65: Alqueire Ventures Fund I, L.P. | G65: Gatilho | H65: Key persons nomeados | I65: 1 — Rafael Antunes | J65: 1 - A&R Exempted Limited Partnership Agreement | K65: 11.1 | L65: — | M65: n/a | N65: Concentração em uma única pessoa | O65: High Confidence
A66: FT-065 | B66: 1 | C66: fundo | D66: fundo | E66: F3 | F66: Alqueire Ventures Fund III, L.P. | G66: Gatilho | H66: Key persons nomeados | I66: 2 — Rafael Antunes, Marina Del Vecchio | J66: 1 - Exempted Limited Partnership Agreement | K66: 11.1 | L66: — | M66: n/a | O66: High Confidence
A67: FT-066 | B67: 1 | C67: fundo | D67: fundo | E67: F4 | F67: Alqueire Ventures Fund IV, L.P. | G67: Gatilho | H67: Key persons nomeados | I67: 3 — Rafael Antunes, Marina Del Vecchio, Tobias Nkemelu. Gatilho: quaisquer 2 dos 3, OU Rafael Antunes isoladamente | J67: 1 - Exempted Limited Partnership Agreement | K67: 11.1 | L67: — | M67: n/a | O67: High Confidence
A68: FT-067 | B68: 1 | C68: fundo | D68: fundo | E68: F1 | F68: Alqueire Ventures Fund I, L.P. | G68: Gatilho | H68: Consequência automática do key person event | I68: NENHUMA consequência automática. Suspensão só ocorre se LPs com 50%+ elegerem por escrito em 90 dias; ausente eleição, o período de investimento continua | J68: 1 - A&R Exempted Limited Partnership Agreement | K68: 11.1 | L68: Suspensão automática do período de investimento; término automático se plano de remediação não aprovado | M68: Sim | N68: Inverte o default: o silêncio favorece o GP | O68: Review
A69: FT-068 | B69: 1 | C69: fundo | D69: fundo | E69: F3 | F69: Alqueire Ventures Fund III, L.P. | G69: Gatilho | H69: Consequência automática do key person event | I69: Suspensão AUTOMÁTICA; plano de remediação em 60 dias; término automático se não aprovado por maioria em 180 dias | J69: 1 - Exempted Limited Partnership Agreement | K69: 11.2 | L69: Suspensão automática do período de investimento; término automático se plano de remediação não aprovado | M69: Não | O69: High Confidence
A70: FT-069 | B70: 1 | C70: fundo | D70: fundo | E70: F4 | F70: Alqueire Ventures Fund IV, L.P. | G70: Gatilho | H70: Consequência automática do key person event | I70: Suspensão AUTOMÁTICA; plano em 45 dias; término automático se não aprovado em 120 dias | J70: 1 - Exempted Limited Partnership Agreement | K70: 11.2 | L70: Suspensão automática do período de investimento; término automático se plano de remediação não aprovado | M70: Não | O70: High Confidence
A71: FT-070 | B71: 1 | C71: fundo | D71: fundo | E71: F1 | F71: Alqueire Ventures Fund I, L.P. | G71: Restrição | H71: Concentração máxima por investida | I71: 20% de Aggregate Commitments, sem ajuste por endividamento | J71: 1 - A&R Exempted Limited Partnership Agreement | K71: 2.2(a) | L71: Limite ajustado para considerar endividamento do fundo | M71: Parcial | O71: High Confidence
A72: FT-071 | B72: 1 | C72: fundo | D72: fundo | E72: F3 | F72: Alqueire Ventures Fund III, L.P. | G72: Restrição | H72: Concentração máxima por investida | I72: 15%, calculado sobre Aggregate Commitments acrescido do endividamento em aberto | J72: 1 - Exempted Limited Partnership Agreement | K72: 2.2(a) | L72: Limite ajustado para considerar endividamento do fundo | M72: Não | N72: Alinhado à atualização de jul/2020 (Investment Limitations) | O72: High Confidence
A73: FT-072 | B73: 1 | C73: fundo | D73: fundo | E73: F4 | F73: Alqueire Ventures Fund IV, L.P. | G73: Restrição | H73: Concentração máxima por investida | I73: 12,5%, com o mesmo ajuste por endividamento | J73: 1 - Exempted Limited Partnership Agreement | K73: 2.2(a) | L73: Limite ajustado para considerar endividamento do fundo | M73: Não | O73: High Confidence
A74: FT-073 | B74: 1 | C74: fundo | D74: fundo | E74: F1 | F74: Alqueire Ventures Fund I, L.P. | G74: Restrição | H74: Limites geográficos e setoriais | I74: Máx. 15% fora da América Latina; vedado listadas fora de spin-off de investida | J74: 1 - A&R Exempted Limited Partnership Agreement | K74: 2.2(b); 2.2(c) | L74: — | M74: n/a | O74: High Confidence
A75: FT-074 | B75: 1 | C75: fundo | D75: fundo | E75: F3 | F75: Alqueire Ventures Fund III, L.P. | G75: Restrição | H75: Limites geográficos e setoriais | I75: Máx. 10% fora da América Latina | J75: 1 - Exempted Limited Partnership Agreement | K75: 2.2(b) | L75: — | M75: n/a | O75: High Confidence
A76: FT-075 | B76: 1 | C76: fundo | D76: fundo | E76: F4 | F76: Alqueire Ventures Fund IV, L.P. | G76: Restrição | H76: Limites geográficos e setoriais | I76: Máx. 7,5% fora da América Latina e Caribe | J76: 1 - Exempted Limited Partnership Agreement | K76: 2.2(b) | L76: — | M76: n/a | O76: High Confidence
A77: FT-076 | B77: 1 | C77: fundo | D77: fundo | E77: F1 | F77: Alqueire Ventures Fund I, L.P. | G77: Restrição | H77: Cross-fund — permitido e consentimento exigido | I77: Permitido com consentimento do LPAC. SEM exigência de valuation independente e SEM política escrita de follow-on | J77: 1 - A&R Exempted Limited Partnership Agreement | K77: 2.2(d) | L77: — | M77: Sim | N77: Já exercido: consentimento do LPAC de 11/03/2022 (Meridiano Logística) registra que não existe política escrita de alocação | O77: Review
A78: FT-077 | B78: 1 | C78: fundo | D78: fundo | E78: F3 | F78: Alqueire Ventures Fund III, L.P. | G78: Restrição | H78: Cross-fund — permitido e consentimento exigido | I78: Permitido com consentimento do LPAC E entrega de valuation preparado por firma independente. Política escrita de follow-on no Schedule D, pro rata por capital disponível | J78: 1 - Exempted Limited Partnership Agreement | K78: 2.2(c); 2.3 | L78: — | M78: Não | O78: High Confidence
A79: FT-078 | B79: 1 | C79: fundo | D79: fundo | E79: F4 | F79: Alqueire Ventures Fund IV, L.P. | G79: Restrição | H79: Cross-fund — permitido e consentimento exigido | I79: Mesma estrutura do Fundo III | J79: 1 - Exempted Limited Partnership Agreement | K79: 2.2(d); 2.5 | L79: — | M79: Não | O79: High Confidence
A80: FT-079 | B80: 1 | C80: fundo | D80: fundo | E80: F1 | F80: Alqueire Ventures Fund I, L.P. | G80: Restrição | H80: Lista de exclusão aplicável | I80: Nenhuma | J80: 1 - A&R Exempted Limited Partnership Agreement | K80: — | L80: — | M80: n/a | N80: Campo ausente — não há cláusula correspondente no documento | O80: High Confidence
A81: FT-080 | B81: 1 | C81: fundo | D81: fundo | E81: F3 | F81: Alqueire Ventures Fund III, L.P. | G81: Restrição | H81: Lista de exclusão aplicável | I81: Nenhuma no LPA. Exclusões existem apenas via side letter (Aurora e Nordvik) e operam como excuse right, não como vedação ao fundo | J81: 1 - Exempted Limited Partnership Agreement | K81: 3.4; side letters | L81: — | M81: n/a | N81: Distinção importante: excuse right protege o LP, não impede o investimento | O81: High Confidence
A82: FT-081 | B82: 1 | C82: fundo | D82: fundo | E82: F4 | F82: Alqueire Ventures Fund IV, L.P. | G82: Restrição | H82: Lista de exclusão aplicável | I82: Exclusion List do Schedule G, com vedação ABSOLUTA — não renunciável pelo LPAC nem por voto de LPs | J82: 1 - Exempted Limited Partnership Agreement | K82: 2.2(c) | L82: — | M82: n/a | N82: Único dos três em que a exclusão vincula o fundo, não só o LP | O82: High Confidence
A83: FT-082 | B83: 1 | C83: fundo | D83: fundo | E83: F1 | F83: Alqueire Ventures Fund I, L.P. | G83: Restrição | H83: Successor fund — restrição | I83: 75% investido, comprometido ou RESERVADO | J83: 1 - A&R Exempted Limited Partnership Agreement | K83: 2.4 | L83: — | M83: Parcial | N83: Inclusão de 'reservado' esvazia o teste, dado que não há limite de reservas | O83: High Confidence
A84: FT-083 | B84: 1 | C84: fundo | D84: fundo | E84: F3 | F84: Alqueire Ventures Fund III, L.P. | G84: Restrição | H84: Successor fund — restrição | I84: 70% investido ou comprometido (sem 'reservado') | J84: 1 - Exempted Limited Partnership Agreement | K84: 2.6 | L84: — | M84: Não | O84: High Confidence
A85: FT-084 | B85: 1 | C85: fundo | D85: fundo | E85: F4 | F85: Alqueire Ventures Fund IV, L.P. | G85: Restrição | H85: Successor fund — restrição | I85: 70% investido ou comprometido | J85: 1 - Exempted Limited Partnership Agreement | K85: 2.6 | L85: — | M85: Não | O85: High Confidence
A86: FT-085 | B86: 1 | C86: fundo | D86: fundo | E86: F1 | F86: Alqueire Ventures Fund I, L.P. | G86: Capital | H86: Subscription line — permitida e limite | I86: 25% de Aggregate Commitments; até 12 meses em aberto. Preferred return corre da data em que a contribuição é RECEBIDA, não do saque | J86: 1 - A&R Exempted Limited Partnership Agreement | K86: 3.5 | L86: Preferred return deve correr da data do saque da linha | M86: Sim | N86: Contraria Principles 3.0 — o GP captura o carrego da linha | O86: Review
A87: FT-086 | B87: 1 | C87: fundo | D87: fundo | E87: F3 | F87: Alqueire Ventures Fund III, L.P. | G87: Capital | H87: Subscription line — permitida e limite | I87: 20%; até 180 dias em aberto. Preferred return corre DA DATA DO SAQUE. IRR reportado com e sem efeito da linha | J87: 1 - Exempted Limited Partnership Agreement | K87: 3.5; 1.1 def. Preferred Return | L87: Preferred return deve correr da data do saque da linha | M87: Não | O87: High Confidence
A88: FT-087 | B88: 1 | C88: fundo | D88: fundo | E88: F4 | F88: Alqueire Ventures Fund IV, L.P. | G88: Capital | H88: Subscription line — permitida e limite | I88: 15%; até 90 dias em aberto. Mesma regra de accrual do Fundo III | J88: 1 - Exempted Limited Partnership Agreement | K88: 3.5 | L88: Preferred return deve correr da data do saque da linha | M88: Não | O88: High Confidence
A89: FT-088 | B89: 1 | C89: fundo | D89: fundo | E89: F1 | F89: Alqueire Ventures Fund I, L.P. | G89: Capital | H89: Excuse rights — quais LPs | I89: NENHUM LP tem excuse right | J89: 1 - A&R Exempted Limited Partnership Agreement | K89: 3.4 | L89: — | M89: n/a | O89: High Confidence
A90: FT-089 | B90: 1 | C90: fundo | D90: fundo | E90: F3 | F90: Alqueire Ventures Fund III, L.P. | G90: Capital | H90: Excuse rights — quais LPs | I90: Por lei/regulação; por política escrita entregue antes da admissão; ou por restrição em side letter. Exercidos: Aurora (tabaco, armas, jogo, carvão térmico) e Nordvik (armas controversas, tabaco, carvão, oil sands, exclusões do GPFG) | J90: 1 - Exempted Limited Partnership Agreement | K90: 3.4; side letters Aurora §1 e Nordvik §1 | L90: — | M90: n/a | O90: High Confidence
A91: FT-090 | B91: 1 | C91: fundo | D91: fundo | E91: F4 | F91: Alqueire Ventures Fund IV, L.P. | G91: Capital | H91: Excuse rights — quais LPs | I91: Mesmas hipóteses + contravenção às E&S Requirements ou às políticas de integridade de DFI | J91: 1 - Exempted Limited Partnership Agreement | K91: 3.4 | L91: — | M91: n/a | O91: High Confidence
A92: FT-091 | B92: 1 | C92: fundo | D92: LP | E92: F1 | F92: Alqueire Ventures Fund I, L.P. | G92: Side letters / MFN | H92: LPs com MFN e tier que destrava | I92: NENHUM. O LPA veda expressamente qualquer direito de eleição e dispensa o GP de divulgar existência ou termos de side letters | J92: 1 - A&R Exempted Limited Partnership Agreement | K92: 15.2; side letter Praia Grande §6 | L92: — | M92: Sim | N92: Ausência total de MFN e de disclosure | O92: Review
A93: FT-092 | B93: 1 | C93: fundo | D93: LP | E93: F3 | F93: Alqueire Ventures Fund III, L.P. | G93: Side letters / MFN | H93: LPs com MFN e tier que destrava | I93: Threshold único de US$20M. Aurora (US$22M) elegível; Meridian (US$45M) elegível com MFN reforçado, sem limitação de tier; Nordvik (US$15M) NÃO elegível | J93: 1 - Exempted Limited Partnership Agreement | K93: 16.2; 6 - Schedule of Side Letter Terms and MFN Election Notice | L93: — | M93: Não | O93: High Confidence
A94: FT-093 | B94: 1 | C94: fundo | D94: LP | E94: F4 | F94: Alqueire Ventures Fund IV, L.P. | G94: Side letters / MFN | H94: LPs com MFN e tier que destrava | I94: TRÊS TIERS: US$25M (relatórios/avisos/confidencialidade), US$50M (+ excuse, exclusion list, transferência, auditoria), US$75M (tudo). Gulf Horizon US$80M e CADS US$75M em Tier 3; BIFR US$50M em Tier 2; BNFP US$45M em Tier 1 | J94: 1 - Exempted Limited Partnership Agreement | K94: 16.2; 7 - Schedule of Side Letter Terms and Tiered MFN Election Notice | L94: — | M94: Não | O94: High Confidence
A95: FT-094 | B95: 1 | C95: fundo | D95: LP | E95: F1 | F95: Alqueire Ventures Fund I, L.P. | G95: Side letters / MFN | H95: Última eleição de MFN executada | I95: n/a — não há direito de eleição | J95: — | K95: — | L95: — | M95: n/a | O95: High Confidence
A96: FT-095 | B96: 1 | C96: fundo | D96: LP | E96: F3 | F96: Alqueire Ventures Fund III, L.P. | G96: Side letters / MFN | H96: Última eleição de MFN executada | I96: EXECUTADA. Schedule entregue 25/09/2023; prazo 25/10/2023; Aurora elegeu N-1/N-2/N-3 (contrassinado 24/10/2023); Meridian elegeu A-1/A-2/A-4/N-1/N-2 (contrassinado 31/10/2023) | J96: 6 - Schedule of Side Letter Terms and MFN Election Notice | K96: Tabela de eleições | L96: — | M96: Não | O96: High Confidence
A97: FT-096 | B97: 1 | C97: fundo | D97: LP | E97: F4 | F97: Alqueire Ventures Fund IV, L.P. | G97: Side letters / MFN | H97: Última eleição de MFN executada | I97: PENDENTE. Schedule entregue 12/06/2026; prazo 12/07/2026; NENHUMA eleição recebida e nenhuma confirmação contrassinada na data do aviso | J97: 7 - Schedule of Side Letter Terms and Tiered MFN Election Notice | K97: Open items (a) | L97: — | M97: n/a | N97: Item aberto — ver aba Obligations | O97: High Confidence
A98: FT-097 | B98: 1 | C98: fundo | D98: fundo | E98: F1 | F98: Alqueire Ventures Fund I, L.P. | G98: Dever recorrente | H98: Prazo do relatório trimestral | I98: 60 dias do fim do trimestre; sem template padrão | J98: 1 - A&R Exempted Limited Partnership Agreement | K98: 14.1(a); 14.2 | L98: — | M98: Sim | O98: Review
A99: FT-098 | B99: 1 | C99: fundo | D99: fundo | E99: F3 | F99: Alqueire Ventures Fund III, L.P. | G99: Dever recorrente | H99: Prazo do relatório trimestral | I99: 45 dias; ILPA Reporting Template para fees/despesas/carry e ILPA Performance Template para performance; IRR com e sem efeito da subscription line | J99: 1 - Exempted Limited Partnership Agreement | K99: 14.1(a); 14.2 | L99: — | M99: Não | O99: High Confidence
A100: FT-099 | B100: 1 | C100: fundo | D100: fundo | E100: F4 | F100: Alqueire Ventures Fund IV, L.P. | G100: Dever recorrente | H100: Prazo do relatório trimestral | I100: 45 dias; ILPA Reporting + Performance + Portfolio Company Template | J100: 1 - Exempted Limited Partnership Agreement | K100: 14.1; 14.2 | L100: — | M100: Não | O100: High Confidence
...

Sheet Side_Letters
A1: SL ID | B1: Nivel | C1: Fund ID | D1: Limited Partner | E1: Commitment (USD) | F1: Classe | G1: Rota | H1: Tier / Elegibilidade MFN | I1: Ref. Provisão | J1: Provisão | K1: Categoria da provisão | L1: Elegível a MFN? | M1: Base da exclusão | N1: Documento Fonte
A2: SL-001 | B2: fundo | C2: F1 | D2: Praia Grande Family Office Ltda. | E2: 3000000 | F2: — | G2: Direta | H2: Sem direito de eleição (LPA veda) | I2: P-1 | J2: Schedule anual de investidas com custo, carrying value e metodologia, em 75 dias do fim do exercício | K2: Reporting | L2: Não | M2: LPA 15.2 veda qualquer eleição | N2: 3 - Side Letter (Praia Grande Family Office)
A3: SL-002 | B3: fundo | C3: F1 | D3: Praia Grande Family Office Ltda. | E3: 3000000 | F3: — | G3: Direta | H3: Sem direito de eleição (LPA veda) | I3: P-2 | J3: Capacity right de 1,5x o commitment no próximo fundo sucessor, exercível em 30 dias | K3: Capacity | L3: Não | M3: LPA 15.2 veda qualquer eleição | N3: 3 - Side Letter (Praia Grande Family Office)
A4: SL-003 | B4: fundo | C4: F1 | D4: Praia Grande Family Office Ltda. | E4: 3000000 | F4: — | G4: Direta | H4: Sem direito de eleição (LPA veda) | I4: P-3 | J4: Co-investimento em 'commercially reasonable efforts', sem prioridade, sem fee e sem carry | K4: Co-investimento | L4: Não | M4: LPA 15.2 veda qualquer eleição | N4: 3 - Side Letter (Praia Grande Family Office)
A5: SL-004 | B5: fundo | C5: F1 | D5: Praia Grande Family Office Ltda. | E5: 3000000 | F5: — | G5: Direta | H5: Sem direito de eleição (LPA veda) | I5: P-4 | J5: Informação para Declaração de Capitais Brasileiros no Exterior | K5: Fiscal | L5: Não | M5: LPA 15.2 veda qualquer eleição | N5: 3 - Side Letter (Praia Grande Family Office)
A6: SL-005 | B6: fundo | C6: F1 | D6: Praia Grande Family Office Ltda. | E6: 3000000 | F6: — | G6: Direta | H6: Sem direito de eleição (LPA veda) | I6: P-5 | J6: Consideração de boa-fé para indicação ao LPAC — nomeação permanece a critério exclusivo do GP | K6: LPAC | L6: Não | M6: LPA 15.2 veda qualquer eleição | N6: 3 - Side Letter (Praia Grande Family Office)
A7: SL-006 | B7: fundo | C7: F1 | D7: Praia Grande Family Office Ltda. | E7: 3000000 | F7: — | G7: Direta | H7: Sem direito de eleição (LPA veda) | I7: P-6 | J7: Renúncia expressa a qualquer direito de MFN e dispensa de disclosure de side letters | K7: MFN | L7: Não | M7: Renúncia expressa no §6 do próprio side letter | N7: 3 - Side Letter (Praia Grande Family Office)
A8: SL-007 | B8: fundo | C8: F3 | D8: Fundo de Pensão Aurora | E8: 22000000 | F8: — | G8: Feeder Fund (FIP) | H8: Elegível — acima do threshold único de US$20M | I8: A-1 | J8: Excuse de tabaco, armas, jogo e carvão térmico (teste de 5% de receita) | K8: Excuse / exclusão | L8: Sim | N8: 3 - Side Letter (Fundo de Pensao Aurora)
A9: SL-008 | B9: fundo | C9: F3 | D9: Fundo de Pensão Aurora | E9: 22000000 | F9: — | G9: Feeder Fund (FIP) | H9: Elegível — acima do threshold único de US$20M | I9: A-2 | J9: ILPA Reporting Template trimestral, em português a pedido; demonstrativo anual de despesas para PREVIC | K9: Reporting | L9: Sim | N9: 3 - Side Letter (Fundo de Pensao Aurora)
A10: SL-009 | B10: fundo | C10: F3 | D10: Fundo de Pensão Aurora | E10: 22000000 | F10: — | G10: Feeder Fund (FIP) | H10: Elegível — acima do threshold único de US$20M | I10: A-3 | J10: Acesso da PREVIC e dos auditores à informação do fundo | K10: Regulatório | L10: Sim | N10: 3 - Side Letter (Fundo de Pensao Aurora)
A11: SL-010 | B11: fundo | C11: F3 | D11: Fundo de Pensão Aurora | E11: 22000000 | F11: — | G11: Feeder Fund (FIP) | H11: Elegível — acima do threshold único de US$20M | I11: A-4 | J11: Carve-out de divulgação por Lei 12.527/2011 — commitment, fluxos e IRR líquido | K11: Confidencialidade | L11: Sim | N11: 3 - Side Letter (Fundo de Pensao Aurora)
A12: SL-011 | B12: fundo | C12: F3 | D12: Fundo de Pensão Aurora | E12: 22000000 | F12: — | G12: Feeder Fund (FIP) | H12: Elegível — acima do threshold único de US$20M | I12: A-5 | J12: Apoio à indicação ao LPAC enquanto detiver 5%+ | K12: LPAC | L12: Não | M12: s.16.3(c) | N12: 3 - Side Letter (Fundo de Pensao Aurora)
A13: SL-012 | B13: fundo | C13: F3 | D13: Fundo de Pensão Aurora | E13: 22000000 | F13: — | G13: Feeder Fund (FIP) | H13: Elegível — acima do threshold único de US$20M | I13: A-6 | J13: Transferência a afiliada ou sucessora por determinação da PREVIC sem consentimento | K13: Transferência | L13: Sim | N13: 3 - Side Letter (Fundo de Pensao Aurora)
A14: SL-013 | B14: fundo | C14: F3 | D14: Meridian Global Partners III (Cayman), L.P. | E14: 45000000 | F14: — | G14: Direta | H14: Elegível — com MFN reforçado, sem limitação de tier | I14: M-1 | J14: Management fee de 1,75% / 1,25% de Invested Cost, por rebate trimestral | K14: Econômico | L14: Não | M14: s.16.3(a) | N14: 4 - Side Letter (Meridian Global Partners)
A15: SL-014 | B15: fundo | C15: F3 | D15: Meridian Global Partners III (Cayman), L.P. | E15: 45000000 | F15: — | G15: Direta | H15: Elegível — com MFN reforçado, sem limitação de tier | I15: M-2 | J15: Prioridade de co-investimento até US$45M, sem fee e sem carry | K15: Co-investimento | L15: Não | M15: s.16.3(b) | N15: 4 - Side Letter (Meridian Global Partners)
A16: SL-015 | B16: fundo | C16: F3 | D16: Meridian Global Partners III (Cayman), L.P. | E16: 45000000 | F16: — | G16: Direta | H16: Elegível — com MFN reforçado, sem limitação de tier | I16: M-3 | J16: Assento no LPAC, com o GP votando a favor da indicação | K16: LPAC | L16: Não | M16: s.16.3(c) | N16: 4 - Side Letter (Meridian Global Partners)
A17: SL-016 | B17: fundo | C17: F3 | D17: Meridian Global Partners III (Cayman), L.P. | E17: 45000000 | F17: — | G17: Direta | H17: Elegível — com MFN reforçado, sem limitação de tier | I17: M-4 | J17: MFN reforçado — elegível a provisão de qualquer LP independentemente do tamanho do commitment | K17: MFN | L17: Não | M17: s.16.3(d) | N17: 4 - Side Letter (Meridian Global Partners)
A18: SL-017 | B18: fundo | C18: F3 | D18: Meridian Global Partners III (Cayman), L.P. | E18: 45000000 | F18: — | G18: Direta | H18: Elegível — com MFN reforçado, sem limitação de tier | I18: M-5 | J18: Capacity right de US$45M no fundo sucessor, exercível em 45 dias | K18: Capacity | L18: Não | M18: s.16.3(b) | N18: 4 - Side Letter (Meridian Global Partners)
A19: SL-018 | B19: fundo | C19: F3 | D19: Meridian Global Partners III (Cayman), L.P. | E19: 45000000 | F19: — | G19: Direta | H19: Elegível — com MFN reforçado, sem limitação de tier | I19: M-6 | J19: Schedule anual de todos os fees pagos ao Manager e afiliadas, com ou sem offset | K19: Reporting | L19: Sim | N19: 4 - Side Letter (Meridian Global Partners)
A20: SL-019 | B20: fundo | C20: F3 | D20: Meridian Global Partners III (Cayman), L.P. | E20: 45000000 | F20: — | G20: Direta | H20: Elegível — com MFN reforçado, sem limitação de tier | I20: M-7 | J20: Aviso de key person event, litígio material e exame regulatório do Manager | K20: Notificação | L20: Sim | N20: 4 - Side Letter (Meridian Global Partners)
A21: SL-020 | B21: fundo | C21: F3 | D21: Meridian Global Partners III (Cayman), L.P. | E21: 45000000 | F21: — | G21: Direta | H21: Elegível — com MFN reforçado, sem limitação de tier | I21: M-8 | J21: Transferência a afiliadas e contas geridas sem consentimento | K21: Transferência | L21: Sim | N21: 4 - Side Letter (Meridian Global Partners)
A22: SL-021 | B22: fundo | C22: F3 | D22: Meridian Global Partners III (Cayman), L.P. | E22: 45000000 | F22: — | G22: Direta | H22: Elegível — com MFN reforçado, sem limitação de tier | I22: M-9 | J22: Aviso de UBTI/ECI e direito a veículo alternativo | K22: Fiscal | L22: Não | M22: s.16.3(d) | N22: 4 - Side Letter (Meridian Global Partners)
A23: SL-022 | B23: fundo | C23: F3 | D23: Nordvik Pensjonskasse AS | E23: 15000000 | F23: — | G23: Direta | H23: NÃO elegível — abaixo do threshold de US$20M | I23: N-1 | J23: Exclusões — armas controversas, tabaco, carvão térmico, oil sands, exclusões de conduta do GPFG | K23: Excuse / exclusão | L23: Sim | N23: 5 - Side Letter (Nordvik Pensjonskasse)
A24: SL-023 | B24: fundo | C24: F3 | D24: Nordvik Pensjonskasse AS | E24: 15000000 | F24: — | G24: Direta | H24: NÃO elegível — abaixo do threshold de US$20M | I24: N-2 | J24: Indicadores anuais de PAI, declaração de risco de sustentabilidade, GHG escopo 1 e 2 em 120 dias | K24: ESG / reporting | L24: Sim | N24: 5 - Side Letter (Nordvik Pensjonskasse)
A25: SL-024 | B25: fundo | C25: F3 | D25: Nordvik Pensjonskasse AS | E25: 15000000 | F25: — | G25: Direta | H25: NÃO elegível — abaixo do threshold de US$20M | I25: N-3 | J25: Política de investimento responsável consistente com UN PRI, com aviso de emenda material | K25: ESG | L25: Sim | N25: 5 - Side Letter (Nordvik Pensjonskasse)
A26: SL-025 | B26: fundo | C26: F3 | D26: Nordvik Pensjonskasse AS | E26: 15000000 | F26: — | G26: Direta | H26: NÃO elegível — abaixo do threshold de US$20M | I26: N-4 | J26: Informação regulatória para o Finanstilsynet | K26: Regulatório | L26: Não | M26: s.16.3(d) | N26: 5 - Side Letter (Nordvik Pensjonskasse)
A27: SL-026 | B27: fundo | C27: F4 | D27: Gulf Horizon Investment Authority | E27: 80000000 | F27: A | G27: Direta | H27: Tier 3 (US$75M+) — pode eleger qualquer provisão | I27: G-1 | J27: Management fee de 1,75% / 1,00% de Invested Cost | K27: Econômico | L27: Não | M27: s.16.3(a) | N27: 5 - Side Letter (Gulf Horizon Investment Authority)
A28: SL-027 | B28: fundo | C28: F4 | D28: Gulf Horizon Investment Authority | E28: 80000000 | F28: A | G28: Direta | H28: Tier 3 (US$75M+) — pode eleger qualquer provisão | I28: G-2 | J28: Não renúncia a imunidade soberana, salvo na arbitragem do Schedule I | K28: Soberano | L28: Não | M28: s.16.3(d) | N28: 5 - Side Letter (Gulf Horizon Investment Authority)
A29: SL-028 | B29: fundo | C29: F4 | D29: Gulf Horizon Investment Authority | E29: 80000000 | F29: A | G29: Direta | H29: Tier 3 (US$75M+) — pode eleger qualquer provisão | I29: G-3 | J29: Identidade e commitment omitidos do registro e dos demais LPs; registro mostra 'Sovereign investor — identity withheld' | K29: Confidencialidade | L29: Sim | N29: 5 - Side Letter (Gulf Horizon Investment Authority)
A30: SL-029 | B30: fundo | C30: F4 | D30: Gulf Horizon Investment Authority | E30: 80000000 | F30: A | G30: Direta | H30: Tier 3 (US$75M+) — pode eleger qualquer provisão | I30: G-4 | J30: Aviso de trade-or-business e direito a veículo alternativo às custas do fundo | K30: Fiscal | L30: Não | M30: s.16.3(d) | N30: 5 - Side Letter (Gulf Horizon Investment Authority)
A31: SL-030 | B31: fundo | C31: F4 | D31: Gulf Horizon Investment Authority | E31: 80000000 | F31: A | G31: Direta | H31: Tier 3 (US$75M+) — pode eleger qualquer provisão | I31: G-5 | J31: Co-investimento até US$120M, sem fee e sem carry | K31: Co-investimento | L31: Não | M31: s.16.3(b) | N31: 5 - Side Letter (Gulf Horizon Investment Authority)
A32: SL-031 | B32: fundo | C32: F4 | D32: Gulf Horizon Investment Authority | E32: 80000000 | F32: A | G32: Direta | H32: Tier 3 (US$75M+) — pode eleger qualquer provisão | I32: G-6 | J32: Capacity right de US$80M no fundo sucessor, em 60 dias | K32: Capacity | L32: Não | M32: s.16.3(b) | N32: 5 - Side Letter (Gulf Horizon Investment Authority)
A33: SL-032 | B33: fundo | C33: F4 | D33: Gulf Horizon Investment Authority | E33: 80000000 | F33: A | G33: Direta | H33: Tier 3 (US$75M+) — pode eleger qualquer provisão | I33: G-7 | J33: Transferência a entidades estatais dos EAU / Abu Dhabi sem consentimento | K33: Transferência | L33: Sim | N33: 5 - Side Letter (Gulf Horizon Investment Authority)
A34: SL-033 | B34: fundo | C34: F4 | D34: Gulf Horizon Investment Authority | E34: 80000000 | F34: A | G34: Direta | H34: Tier 3 (US$75M+) — pode eleger qualquer provisão | I34: G-8 | J34: Recebe materiais do LPAC sem indicar membro; renuncia ao direito de indicar | K34: LPAC | L34: Sim | N34: 5 - Side Letter (Gulf Horizon Investment Authority)
A35: SL-034 | B35: fundo | C35: F4 | D35: Corporación Andina de Desarrollo Sostenible (CADS) | E35: 75000000 | F35: B | G35: Direta | H35: Tier 3 (US$75M+) — pode eleger qualquer provisão | I35: C-1 | J35: Class B — carried interest de 17,5% | K35: Econômico | L35: Não | M35: s.16.3(a) | N35: 2 - Side Letter (CADS)
A36: SL-035 | B36: fundo | C36: F4 | D36: Corporación Andina de Desarrollo Sostenible (CADS) | E36: 75000000 | F36: B | G36: Direta | H36: Tier 3 (US$75M+) — pode eleger qualquer provisão | I36: C-2 | J36: CADS Performance Standards e manutenção de ESMS | K36: E&S | L36: Não | M36: s.16.3(d) | N36: 2 - Side Letter (CADS)
A37: SL-036 | B37: fundo | C37: F4 | D37: Corporación Andina de Desarrollo Sostenible (CADS) | E37: 75000000 | F37: B | G37: Direta | H37: Tier 3 (US$75M+) — pode eleger qualquer provisão | I37: C-3 | J37: Certificado por investimento confirmando inclusão dos flow-down covenants, em 60 dias, com extrato da documentação | K37: E&S | L37: Não | M37: s.16.3(d) | N37: 2 - Side Letter (CADS)
A38: SL-037 | B38: fundo | C38: F4 | D38: Corporación Andina de Desarrollo Sostenible (CADS) | E38: 75000000 | F38: B | G38: Direta | H38: Tier 3 (US$75M+) — pode eleger qualquer provisão | I38: C-4 | J38: Notificação prévia de 15 dias úteis e direito de objeção escrita em investimento Categoria A | K38: E&S | L38: Não | M38: s.16.3(d) | N38: 2 - Side Letter (CADS)
A39: SL-038 | B39: fundo | C39: F4 | D39: Corporación Andina de Desarrollo Sostenible (CADS) | E39: 75000000 | F39: B | G39: Direta | H39: Tier 3 (US$75M+) — pode eleger qualquer provisão | I39: C-5 | J39: Relatório E&S anual em 90 dias; notificação de incidente em 5 dias úteis | K39: Reporting | L39: Sim | N39: 2 - Side Letter (CADS)
A40: SL-039 | B40: fundo | C40: F4 | D40: Corporación Andina de Desarrollo Sostenible (CADS) | E40: 75000000 | F40: B | G40: Direta | H40: Tier 3 (US$75M+) — pode eleger qualquer provisão | I40: C-6 | J40: Screening de integridade e sanções contra listas de debarment das MDBs | K40: Integridade | L40: Não | M40: s.16.3(d) | N40: 2 - Side Letter (CADS)
A41: SL-040 | B41: fundo | C41: F4 | D41: Corporación Andina de Desarrollo Sostenible (CADS) | E41: 75000000 | F41: B | G41: Direta | H41: Tier 3 (US$75M+) — pode eleger qualquer provisão | I41: C-7 | J41: Auditoria, inspeção e site visit estendidos a agentes | K41: Auditoria | L41: Sim | N41: 2 - Side Letter (CADS)
A42: SL-041 | B42: fundo | C42: F4 | D42: Corporación Andina de Desarrollo Sostenible (CADS) | E42: 75000000 | F42: B | G42: Direta | H42: Tier 3 (US$75M+) — pode eleger qualquer provisão | I42: C-8 | J42: Direito de indicar 1 membro do LPAC enquanto detiver 4%+ | K42: LPAC | L42: Não | M42: s.16.3(c) | N42: 2 - Side Letter (CADS)
A43: SL-042 | B43: fundo | C43: F4 | D43: Corporación Andina de Desarrollo Sostenible (CADS) | E43: 75000000 | F43: B | G43: Direta | H43: Tier 3 (US$75M+) — pode eleger qualquer provisão | I43: C-9 | J43: Suspensão de aporte por decisão do próprio órgão de governança sem consequência de default | K43: Capital | L43: Não | M43: s.16.3(d) | N43: 2 - Side Letter (CADS)
A44: SL-043 | B44: fundo | C44: F4 | D44: Banco Interamericano de Fomento Regional (BIFR) | E44: 50000000 | F44: B | G44: Direta | H44: Tier 2 (US$50M+) — reporting, aviso, confidencialidade, disclosure, excuse, exclusion list, transferência, auditoria | I44: B-1 | J44: Mandato de desenvolvimento — mín. 60% das contribuições em investidas dos países do Schedule 2; shortfall por 2 exercícios gera excuse right | K44: Mandato | L44: Não | M44: s.16.3(d) | N44: 3 - Side Letter (BIFR)
A45: SL-044 | B45: fundo | C45: F4 | D45: Banco Interamericano de Fomento Regional (BIFR) | E45: 50000000 | F45: B | G45: Direta | H45: Tier 2 (US$50M+) — reporting, aviso, confidencialidade, disclosure, excuse, exclusion list, transferência, auditoria | I45: B-2 | J45: Relatório anual de impacto — emprego direto e indireto, participação de mulheres, MPMEs na cadeia, classificação de finanças climáticas MDB | K45: Reporting | L45: Sim | N45: 3 - Side Letter (BIFR)
A46: SL-045 | B46: fundo | C46: F4 | D46: Banco Interamericano de Fomento Regional (BIFR) | E46: 50000000 | F46: B | G46: Direta | H46: Tier 2 (US$50M+) — reporting, aviso, confidencialidade, disclosure, excuse, exclusion list, transferência, auditoria | I46: B-3 | J46: Screening contra lista de sancionados e cross-debarment das MDBs; alienação de investida que passe a constar, mediante consulta | K46: Integridade | L46: Não | M46: s.16.3(d) | N46: 3 - Side Letter (BIFR)
A47: SL-046 | B47: fundo | C47: F4 | D47: Banco Interamericano de Fomento Regional (BIFR) | E47: 50000000 | F47: B | G47: Direta | H47: Tier 2 (US$50M+) — reporting, aviso, confidencialidade, disclosure, excuse, exclusion list, transferência, auditoria | I47: B-4 | J47: Retenção de registros de integridade por todo o Term e cooperação com a Office of Institutional Integrity | K47: Integridade | L47: Não | M47: s.16.3(d) | N47: 3 - Side Letter (BIFR)
A48: SL-047 | B48: fundo | C48: F4 | D48: Banco Interamericano de Fomento Regional (BIFR) | E48: 50000000 | F48: B | G48: Direta | H48: Tier 2 (US$50M+) — reporting, aviso, confidencialidade, disclosure, excuse, exclusion list, transferência, auditoria | I48: B-5 | J48: Direito de indicar 1 membro do LPAC | K48: LPAC | L48: Não | M48: s.16.3(c) | N48: 3 - Side Letter (BIFR)
A49: SL-048 | B49: fundo | C49: F4 | D49: Banco Interamericano de Fomento Regional (BIFR) | E49: 50000000 | F49: B | G49: Direta | H49: Tier 2 (US$50M+) — reporting, aviso, confidencialidade, disclosure, excuse, exclusion list, transferência, auditoria | I49: B-6 | J49: Auditoria e inspeção estendidas à Office of Evaluation and Oversight | K49: Auditoria | L49: Sim | N49: 3 - Side Letter (BIFR)
A50: SL-049 | B50: fundo | C50: F4 | D50: Banco Nacional de Fomento Produtivo (BNFP) | E50: 45000000 | F50: B | G50: Feeder Fund (FIP) apenas | H50: Tier 1 (US$25M+) — apenas reporting, aviso, confidencialidade e disclosure | I50: N4-1 | J50: Participação exclusivamente via Feeder Fund sob CVM 175; regulamento não emendável de forma adversa sem consentimento | K50: Estrutura | L50: Não | M50: s.16.3(d) | N50: 4 - Side Letter (BNFP)
A51: SL-050 | B51: fundo | C51: F4 | D51: Banco Nacional de Fomento Produtivo (BNFP) | E51: 45000000 | F51: B | G51: Feeder Fund (FIP) apenas | H51: Tier 1 (US$25M+) — apenas reporting, aviso, confidencialidade e disclosure | I51: N4-2 | J51: Class B — carried interest de 17,5% | K51: Econômico | L51: Não | M51: s.16.3(a) | N51: 4 - Side Letter (BNFP)
A52: SL-051 | B52: fundo | C52: F4 | D52: Banco Nacional de Fomento Produtivo (BNFP) | E52: 45000000 | F52: B | G52: Feeder Fund (FIP) apenas | H52: Tier 1 (US$25M+) — apenas reporting, aviso, confidencialidade e disclosure | I52: N4-3 | J52: Destinação de recursos — mín. 70% em investidas brasileiras e mín. 20% fora de SP e RJ, certificado anualmente e confirmado pelos auditores | K52: Mandato | L52: Não | M52: s.16.3(d) | N52: 4 - Side Letter (BNFP)
A53: SL-052 | B53: fundo | C53: F4 | D53: Banco Nacional de Fomento Produtivo (BNFP) | E53: 45000000 | F53: B | G53: Feeder Fund (FIP) apenas | H53: Tier 1 (US$25M+) — apenas reporting, aviso, confidencialidade e disclosure | I53: N4-4 | J53: Vedação de aplicação em Exclusion List, em compra de participação de sócio existente fora de primária, e em investida inadimplente com a administração federal | K53: Mandato | L53: Não | M53: s.16.3(d) | N53: 4 - Side Letter (BNFP)
A54: SL-053 | B54: fundo | C54: F4 | D54: Banco Nacional de Fomento Produtivo (BNFP) | E54: 45000000 | F54: B | G54: Feeder Fund (FIP) apenas | H54: Tier 1 (US$25M+) — apenas reporting, aviso, confidencialidade e disclosure | I54: N4-5 | J54: Todo o reporting em português, incluindo posição de destinação de recursos | K54: Reporting | L54: Sim | N54: 4 - Side Letter (BNFP)
A55: SL-054 | B55: fundo | C55: F4 | D55: Banco Nacional de Fomento Produtivo (BNFP) | E55: 45000000 | F55: B | G55: Feeder Fund (FIP) apenas | H55: Tier 1 (US$25M+) — apenas reporting, aviso, confidencialidade e disclosure | I55: N4-6 | J55: Acesso de TCU, CGU e auditoria interna aos livros do feeder, do fundo e de investidas, com site visits | K55: Auditoria | L55: Não | M55: s.16.3(d) | N55: 4 - Side Letter (BNFP)
A56: SL-055 | B56: fundo | C56: F4 | D56: Banco Nacional de Fomento Produtivo (BNFP) | E56: 45000000 | F56: B | G56: Feeder Fund (FIP) apenas | H56: Tier 1 (US$25M+) — apenas reporting, aviso, confidencialidade e disclosure | I56: N4-7 | J56: Reps de Lei 12.846/2013 nas investidas e notificação em 5 dias úteis | K56: Integridade | L56: Não | M56: s.16.3(d) | N56: 4 - Side Letter (BNFP)
A57: SL-056 | B57: fundo | C57: F4 | D57: Banco Nacional de Fomento Produtivo (BNFP) | E57: 45000000 | F57: B | G57: Feeder Fund (FIP) apenas | H57: Tier 1 (US$25M+) — apenas reporting, aviso, confidencialidade e disclosure | I57: N4-8 | J57: Direito de indicar 1 membro do LPAC, que deve ser servidor de carreira | K57: LPAC | L57: Não | M57: s.16.3(c) | N57: 4 - Side Letter (BNFP)

Sheet Obligations
B2: Estado derivado — NÃO é termo extraído
B3: Recalcula com o relógio, não com assinatura de documento. Célula vazia aqui não significa 'nada vence' — a coluna Status_Calculo distingue as duas condições.
A5: Obl ID | B5: Fund ID | C5: Obrigação | D5: Fonte da regra | E5: Cláusula | F5: Gatilho | G5: Periodicidade | H5: Insumo necessário | I5: Quem produz | J5: Evidência do último cumprimento | K5: Próximo vencimento | L5: Status_Calculo | M5: Status
A6: OB-001 | B6: F4 | C6: Certificado anual ao LPAC confirmando vigência das garantias de clawback e suficiência patrimonial dos garantidores | D6: LPA Fundo IV | E6: 8.6 | F6: Fim de exercício | G6: Anual | H6: Confirmação de vigência das garantias + demonstração de patrimônio de cada garantidor | I6: GP / Manager (CFO) | J6: NENHUMA — período encerrado em 31/12/2025 não entregue | K6: Vencido | L6: Calculado | M6: EM ATRASO
A7: OB-002 | B7: F4 | C7: No-objection do BNFP ao ESMS submetido | D7: E&S Supervision Agreement | E7: §1 | F7: Submissão do ESMS | G7: Evento único | H7: Manifestação escrita do BNFP | I7: BNFP | J7: ESMS submetido 24/06/2026; no-objection do BNFP pendente | K7: Pendente sem prazo definido | L7: Calculado | M7: PENDENTE
A8: OB-003 | B8: F4 | C8: Prazo final para eleição de MFN pelos LPs | D8: LPA Fundo IV | E8: 16.2 | F8: Entrega do schedule em 12/06/2026 | G8: Evento único | H8: Eleições escritas dos LPs elegíveis | I8: LPs (recebimento); GP contrassina | J8: Schedule entregue 12/06/2026; nenhuma eleição recebida | K8: 12/07/2026 | L8: Calculado | M8: PRAZO ABERTO
A9: OB-004 | B9: F4 | C9: Relatório E&S anual às três DFIs | D9: LPA Fundo IV + E&S Agreement | E9: 2.3(d); E&S §4 | F9: 90 dias do fim do exercício | G9: Anual | H9: Dados de ESMS, categorização, planos de ação, incidentes, grievances, força de trabalho, GHG | I9: E&S officer do Manager; investidas via flow-down | J9: Exercício 2025 entregue 30/03/2026 | K9: 31/03/2027 | L9: Calculado | M9: EM DIA
A10: OB-005 | B10: F4 | C10: Certificado de flow-down por investimento | D10: E&S Supervision Agreement | E10: §3 | F10: Cada closing de investimento | G10: Por evento (60 dias do closing) | H10: Extrato da documentação definitiva com as cláusulas de flow-down | I10: Jurídico + Manager | J10: n/a — depende de novo investimento | K10: Por evento | L10: Não aplicável até novo closing | M10: MONITORAR
A11: OB-006 | B11: F4 | C11: Notificação prévia à CADS de investimento Categoria A | D11: Side letter CADS | E11: §4 | F11: 15 dias úteis antes do closing | G11: Por evento | H11: Categorização E&S do target | I11: E&S officer do Manager | J11: n/a | K11: Por evento | L11: Não aplicável até novo Categoria A | M11: MONITORAR
A12: OB-007 | B12: F4 | C12: Certificação anual de destinação de recursos ao BNFP (70% Brasil / 20% fora SP-RJ) | D12: Side letter BNFP | E12: §3 | F12: Fim de exercício | G12: Anual | H12: Posição de carteira por jurisdição e por estado + confirmação dos auditores do feeder | I12: Manager + auditores do feeder | J12: Exercício 2025: certificado em 28/04/2026 | K12: 30/04/2027 | L12: Calculado | M12: EM DIA
A13: OB-008 | B13: F4 | C13: Relatório anual de impacto ao BIFR | D13: Side letter BIFR | E13: §3 | F13: 90 dias do fim do exercício | G13: Anual | H13: Indicadores de emprego, participação feminina, MPMEs na cadeia, classificação climática MDB | I13: Manager; investidas via flow-down | J13: Exercício 2025 entregue 27/03/2026 | K13: 31/03/2027 | L13: Calculado | M13: EM DIA
A14: OB-009 | B14: F3 | C14: Relatório trimestral em ILPA Reporting Template | D14: LPA Fundo III | E14: 14.1(a); 14.2 | F14: 45 dias do fim do trimestre | G14: Trimestral | H14: Dados de fees, despesas, carry, performance; IRR com e sem subscription line | I14: CFO + administrador | J14: T1 2026 entregue 14/05/2026 | K14: 14/08/2026 | L14: Calculado | M14: EM DIA
A15: OB-010 | B15: F3 | C15: Registro trimestral de LPs a todos os LPs (Partnership + Feeder) | D15: LPA Fundo III | E15: 14.3 | F15: Trimestral | G15: Trimestral | H15: Registro de LPs do fundo e do feeder com nome e commitment | I15: Administrador do fundo + administrador do FIP | J15: T1 2026 entregue 14/05/2026 | K15: 14/08/2026 | L15: Calculado | M15: EM DIA
A16: OB-011 | B16: F3 | C16: Reunião do LPAC com revisão de valuation de cada investida | D16: LPA Fundo III | E16: 9.2(d) | F16: Mín. 1 por ano civil, de 2 reuniões | G16: Anual | H16: Pasta de valuation por investida sob IPEV | I16: Manager + auditores | J16: Realizada 19/11/2025 | K16: Até 31/12/2026 | L16: Calculado | M16: EM DIA
... A19: OB-014 | B19: gestora | C19: Política escrita de alocação de follow-on (solicitada pelo LPAC do Fundo I) | D19: Advisory Committee Written Consent 11/03/2022 | E19: §2 | F19: Solicitação do LPAC — sem prazo contratual | G19: Evento único | H19: Política escrita de alocação | I19: Manager / Jurídico | J19: Não adotada à data do consent; Fundos III e IV já têm política no Schedule D | K19: Sem prazo — solicitação advisory | L19: Calculado | M19: ABERTO

Sheet Dicionario_Termos_Fundos
A1: Dic ID | B1: Camada | C1: Escopo | D1: Categoria | E1: Termo Canônico | F1: Definição em linguagem simples | G1: Sinônimos / como aparece no doc | H1: Referência ILPA | I1: Onde procurar (seção típica)
A2: DF-001 | B2: 1 | C2: fundo | D2: Economia | E2: Step-down do management fee | F2: Redução da taxa de administração depois que o fundo para de investir. O que importa não é só o percentual, é a base: sobre capital comprometido ou sobre custo do que ainda está na carteira. | G2: step-down; reduction in management fee; post-commitment period fee | H2: A redução deve considerar realizações totais ou parciais, para que a taxa caia conforme a carteira é realizada | I2: Artigo de Management Fee; def. de Invested Cost
A3: DF-002 | B3: 1 | C3: fundo | D3: Economia | E3: Tipo de waterfall | F3: Se o GP recebe carry a cada investimento vendido (deal-by-deal) ou só depois que todo o capital do fundo voltou (whole-of-fund). Deal-by-deal antecipa carry e aumenta risco de clawback. | G3: distribution waterfall; European vs American waterfall; fund-as-a-whole; Portfolio Investment-by-Portfolio Investment basis | H3: Whole-of-fund, para limitar a possibilidade de clawback | I3: Artigo de Distributions, primeira seção
A4: DF-003 | B4: 1 | C4: fundo | D4: Economia | E4: Carry escrow | F4: Parte do carry que fica retida em conta separada até o fim do fundo, como garantia de que o GP conseguirá devolver se tiver recebido demais. | G4: escrow; holdback; carried interest escrow account | H4: 30% das distribuições de carry | I4: Seção de escrow, junto ao clawback
A5: DF-004 | B5: 1 | C5: fundo | D5: Economia | E5: Garantia do clawback | F5: Como a obrigação de devolver carry excedente está garantida: escrow, garantia pessoal dos sócios, ou nada. Cláusula de clawback sem garantia é promessa sem lastro. | G5: clawback guarantee; personal guarantee; joint and several; several but not joint; giveback security | H5: Garantia pessoal dos beneficiários finais do carry, opcionalmente em base solidária | I5: Seção imediatamente após o clawback
A6: DF-005 | B6: 1 | C6: fundo | D6: Quórum | E6: No-fault removal | F6: Quórum de LPs necessário para trocar o GP sem alegar culpa, e o que acontece com o carry dele. Quórum alto sem haircut torna a cláusula decorativa. | G6: removal without cause; no-fault divorce; removal of the general partner | H6: Previsto, sem pagamento de fee adicional após remoção; opção de haircut no carry por supermaioria | I6: Artigo de Key Person / Removal
A7: DF-006 | B7: 1 | C7: fundo | D7: Gatilho | E7: Key person event | F7: O que dispara quando uma pessoa-chave sai, e se a consequência é automática ou depende de os LPs agirem. Se depende de ação, o silêncio favorece o GP. | G7: key person; key man; cessation of service; suspension of the commitment period | H7: Suspensão automática do período de investimento; término automático se o plano de remediação não for aprovado no prazo | I7: Artigo de Key Person
A8: DF-007 | B8: 1 | C8: fundo | D8: Restrição | E8: Cross-fund investment | F8: Fundo novo investindo em empresa que já é do fundo anterior. É o conflito de interesse mais comum e mais mal documentado numa gestora com múltiplos fundos. | G8: cross-fund investment; investment in a Portfolio Company held by another fund; affiliated fund transaction | H8: Requer consentimento do LPAC; ILPA veda pre-clearance de conflito | I8: Investment Limitations; Conflicts / Affiliate Transactions
A9: DF-008 | B9: 1 | C9: LP | D9: Side letters / MFN | E9: MFN — tier que destrava | F9: O tamanho de compromisso a partir do qual um LP pode 'pegar' as vantagens dadas a outro LP. Pode ser threshold único ou escada de tiers com escopos diferentes. | G9: most-favoured-nation; MFN election; election right; commitment threshold; tiered MFN | H9: Não há posição de tier específica; o Model LPA busca reduzir a extensão das side letters | I9: Artigo final de Side Letters; e o schedule de MFN
A10: DF-009 | B10: 2 | C10: fundo | D10: Governança | E10: Direitos do LPAC | F10: Se o comitê consultivo tem dentes: pode reunir sem o GP na sala, contratar assessor pago pelo fundo, e estar coberto por seguro. Sem os três, é comitê de fachada. | G10: advisory committee; LPAC; in camera; advisers at the expense of the Partnership | H10: Os três: reunião in camera, assessores às custas do fundo, seguro como despesa do fundo | I10: Artigo de Governance / Advisory Committee
A11: DF-010 | B11: 2 | C11: fundo | D11: Conduta | E11: Standard of care | F11: Se o documento reconhece dever fiduciário do GP ou o elimina expressamente e o substitui por boa-fé. Em Cayman e Delaware a eliminação é permitida — e comum. | G11: standard of care; fiduciary duty; duties modified, limited and eliminated; good faith | H11: Dever fiduciário reconhecido; o GP não pode antepor seu interesse ao do fundo ou dos LPs no exercício de discricionariedade | I11: Artigo de Standard of Care / Exculpation
A12: DF-011 | B12: 2 | C12: fundo | D12: Capital | E12: Subscription line e accrual do preferred | F12: Linha de crédito que adianta capital antes de chamar o LP. A pergunta que importa: o preferred return conta da data do saque da linha ou da data em que o LP põe dinheiro? A diferença é carry. | G12: subscription facility; capital call facility; bridge line; capital at risk | H12: O preferred return deve correr da data em que o capital está em risco, isto é, do saque da linha | I12: Seção de Capital; e def. de Preferred Return
A13: DF-012 | B13: 2 | C13: fundo | D13: Transparência | E13: Comunicação entre LPs | F13: Se os LPs podem conversar entre si sobre o fundo. Restringir isso impede que exerçam direitos de governança coletivamente. | G13: communication among Limited Partners; LP-to-LP communication; confidentiality | H13: Expressamente permitida; e o GP deve fornecer lista de LPs trimestralmente | I13: Artigo de Reports / Confidentiality
... A17: DF-016 | B17: 3 | C17: fundo | D17: Fiscal | E17: Listed transactions / prohibited tax shelter | F17: Linguagem fiscal americana padrão, tipicamente vinda de side letter. Presente ou ausente — sem gradação útil. | G17: listed transaction; prohibited tax shelter transaction; 6707A; 4965 | H17: Linguagem típica de side letter incorporada ao corpo do Model LPA | I17: Artigo de Tax

Sheet Stats_Fundos
B2: Estatísticas — calculadas por fórmula sobre Fund_Terms e Side_Letters
B3: Editar apenas as células azuis. Todo o resto é fórmula e recalcula quando as abas de origem mudam.
B5: Termos por camada
B6: Camada | C6: Descrição | D6: Termos únicos | E6: Linhas (3 fundos)
B7: 1 | C7: Dashboard | D7: =COUNTIFS(Fund_Terms!$B$2:$B$205,$B7,Fund_Terms!$E$2:$E$205,"F1") -> 34 | E7: =COUNTIF(Fund_Terms!$B$2:$B$205,$B7) -> 102
B8: 2 | C8: Planilha, fora da tela | D8: =COUNTIFS(Fund_Terms!$B$2:$B$205,$B8,Fund_Terms!$E$2:$E$205,"F1") -> 24 | E8: =COUNTIF(Fund_Terms!$B$2:$B$205,$B8) -> 72
B9: 3 | C9: Ponteiro apenas | D9: =COUNTIFS(Fund_Terms!$B$2:$B$205,$B9,Fund_Terms!$E$2:$E$205,"F1") -> 10 | E9: =COUNTIF(Fund_Terms!$B$2:$B$205,$B9) -> 30
C10: Total | D10: =SUM(D7:D9) -> 68 | E10: =SUM(E7:E9) -> 204
B12: Desvios em relação à referência ILPA, por fundo
B13: Fund ID | C13: Fundo | D13: Desvio = Sim | E13: Desvio = Parcial | F13: Desvio = Não | G13: % de desvio claro
B14: F1 | C14: =INDEX(Fund_Terms!$F$2:$F$205,MATCH($B14,Fund_Terms!$E$2:$E$205,0)) -> Alqueire Ventures Fund I, L.P. | D14: =COUNTIFS(Fund_Terms!$E$2:$E$205,$B14,Fund_Terms!$M$2:$M$205,"Sim") -> 34 | E14: =COUNTIFS(Fund_Terms!$E$2:$E$205,$B14,Fund_Terms!$M$2:$M$205,"Parcial") -> 5 | F14: =COUNTIFS(Fund_Terms!$E$2:$E$205,$B14,Fund_Terms!$M$2:$M$205,"Não") -> 2 | G14: =IFERROR(D14/(D14+E14+F14),0) -> 0.82926829
B15: F3 | C15: =INDEX(Fund_Terms!$F$2:$F$205,MATCH($B15,Fund_Terms!$E$2:$E$205,0)) -> Alqueire Ventures Fund III, L.P. | D15: =COUNTIFS(Fund_Terms!$E$2:$E$205,$B15,Fund_Terms!$M$2:$M$205,"Sim") -> 0 | E15: =COUNTIFS(Fund_Terms!$E$2:$E$205,$B15,Fund_Terms!$M$2:$M$205,"Parcial") -> 1 | F15: =COUNTIFS(Fund_Terms!$E$2:$E$205,$B15,Fund_Terms!$M$2:$M$205,"Não") -> 41 | G15: =IFERROR(D15/(D15+E15+F15),0) -> 0
B16: F4 | C16: =INDEX(Fund_Terms!$F$2:$F$205,MATCH($B16,Fund_Terms!$E$2:$E$205,0)) -> Alqueire Ventures Fund IV, L.P. | D16: =COUNTIFS(Fund_Terms!$E$2:$E$205,$B16,Fund_Terms!$M$2:$M$205,"Sim") -> 0 | E16: =COUNTIFS(Fund_Terms!$E$2:$E$205,$B16,Fund_Terms!$M$2:$M$205,"Parcial") -> 2 | F16: =COUNTIFS(Fund_Terms!$E$2:$E$205,$B16,Fund_Terms!$M$2:$M$205,"Não") -> 40 | G16: =IFERROR(D16/(D16+E16+F16),0) -> 0
B18: Desvios de Camada 1 (os que aparecem no dashboard)
B19: Fund ID | C19: Desvio = Sim na Camada 1
B20: F1 | C20: =COUNTIFS(Fund_Terms!$E$2:$E$205,$B20,Fund_Terms!$M$2:$M$205,"Sim",Fund_Terms!$B$2:$B$205,1) -> 19
B21: F3 | C21: =COUNTIFS(Fund_Terms!$E$2:$E$205,$B21,Fund_Terms!$M$2:$M$205,"Sim",Fund_Terms!$B$2:$B$205,1) -> 0
B22: F4 | C22: =COUNTIFS(Fund_Terms!$E$2:$E$205,$B22,Fund_Terms!$M$2:$M$205,"Sim",Fund_Terms!$B$2:$B$205,1) -> 0
B24: Side letters e MFN
B25: Fund ID | C25: Provisões em side letter | D25: Elegíveis a MFN | E25: Excluídas do MFN | F25: LPs com side letter
B26: F1 | C26: =COUNTIF(Side_Letters!$C$2:$C$57,$B26) -> 6 | D26: =COUNTIFS(Side_Letters!$C$2:$C$57,$B26,Side_Letters!$L$2:$L$57,"Sim") -> 0 | E26: =COUNTIFS(Side_Letters!$C$2:$C$57,$B26,Side_Letters!$L$2:$L$57,"Não") -> 6 | F26: =INDEX(Funds!$K$2:$K$4,MATCH($B26,Funds!$A$2:$A$4,0)) -> 1
B27: F3 | C27: =COUNTIF(Side_Letters!$C$2:$C$57,$B27) -> 19 | D27: =COUNTIFS(Side_Letters!$C$2:$C$57,$B27,Side_Letters!$L$2:$L$57,"Sim") -> 11 | E27: =COUNTIFS(Side_Letters!$C$2:$C$57,$B27,Side_Letters!$L$2:$L$57,"Não") -> 8 | F27: =INDEX(Funds!$K$2:$K$4,MATCH($B27,Funds!$A$2:$A$4,0)) -> 3
B28: F4 | C28: =COUNTIF(Side_Letters!$C$2:$C$57,$B28) -> 31 | D28: =COUNTIFS(Side_Letters!$C$2:$C$57,$B28,Side_Letters!$L$2:$L$57,"Sim") -> 8 | E28: =COUNTIFS(Side_Letters!$C$2:$C$57,$B28,Side_Letters!$L$2:$L$57,"Não") -> 23 | F28: =INDEX(Funds!$K$2:$K$4,MATCH($B28,Funds!$A$2:$A$4,0)) -> 4
B30: Compromissos por LP com side letter
B31: Fund ID | C31: Soma dos commitments com side letter (USD) | D31: Aggregate Commitments (USD) | E31: % do fundo com side letter
B32: F1 | C32: =SUMPRODUCT((Side_Letters!$C$2:$C$57=$B32)/COUNTIFS(Side_Letters!$C$2:$C$57,Side_Letters!$C$2:$C$57&"",Side_Letters!$D$2:$D$57,Side_Letters!$D$2:$D$57&"")*Side_Letters!$E$2:$E$57) -> 3000000 | D32: =INDEX(Funds!$G$2:$G$4,MATCH($B32,Funds!$A$2:$A$4,0)) -> 45000000 | E32: =IFERROR(C32/D32,0) -> 0.066666667
B33: F3 | C33: =SUMPRODUCT((Side_Letters!$C$2:$C$57=$B33)/COUNTIFS(Side_Letters!$C$2:$C$57,Side_Letters!$C$2:$C$57&"",Side_Letters!$D$2:$D$57,Side_Letters!$D$2:$D$57&"")*Side_Letters!$E$2:$E$57) -> 82000000 | D33: =INDEX(Funds!$G$2:$G$4,MATCH($B33,Funds!$A$2:$A$4,0)) -> 180000000 | E33: =IFERROR(C33/D33,0) -> 0.45555556
B34: F4 | C34: =SUMPRODUCT((Side_Letters!$C$2:$C$57=$B34)/COUNTIFS(Side_Letters!$C$2:$C$57,Side_Letters!$C$2:$C$57&"",Side_Letters!$D$2:$D$57,Side_Letters!$D$2:$D$57&"")*Side_Letters!$E$2:$E$57) -> 250000000 | D34: =INDEX(Funds!$G$2:$G$4,MATCH($B34,Funds!$A$2:$A$4,0)) -> 320000000 | E34: =IFERROR(C34/D34,0) -> 0.78125
B36: Obrigações por status
B37: Status | C37: Contagem
B38: EM DIA | C38: =COUNTIF(Obligations!$M$6:$M$19,$B38) -> 7
B39: EM ATRASO | C39: =COUNTIF(Obligations!$M$6:$M$19,$B39) -> 1
B40: PENDENTE | C40: =COUNTIF(Obligations!$M$6:$M$19,$B40) -> 1
B41: PRAZO ABERTO | C41: =COUNTIF(Obligations!$M$6:$M$19,$B41) -> 1
B42: MONITORAR | C42: =COUNTIF(Obligations!$M$6:$M$19,$B42) -> 2
B43: VERIFICAR | C43: =COUNTIF(Obligations!$M$6:$M$19,$B43) -> 1
B44: ABERTO | C44: =COUNTIF(Obligations!$M$6:$M$19,$B44) -> 1
B45: Soma dos status acima | C45: =SUM(C38:C44) -> 14
B46: Obrigações na aba Obligations | C46: =COUNTA(Obligations!$A$6:$A$19) -> 14
B47: Reconciliação — status fora da lista | C47: =IF(C45=C46,"OK","ATENCAO: "&C46-C45&" obrigacao(oes) com status nao previsto — nao aparecem em nenhuma contagem acima") -> OK
