Workbook

Sheet README
B2: Deal Terms Golden Dataset — MVP Sample
B3: Extracted terms from 6 sample deal packages, structured as a prototype of the golden dataset for the deals dashboard.
B5: Purpose | C5: This workbook simulates the curated, human-reviewed 'golden dataset' that would sit behind the dashboard. Each row in the Terms sheet corresponds to a term extracted from an underlying document, with a citation to the source document and section, mirroring the extraction + review workflow discussed for the MVP.
B6: Deals sheet | C6: One row per deal package. Deal Type, Investment Amount, and Valuation are the fields most useful for filtering (by GP, vintage, round, size).
B7: Terms sheet | C7: One row per extracted term, tagged by Category. The 'Included' column (Y/N) is what powers frequency stats (e.g. 'how many deals have MFN'). Company and Deal Type are pulled via formula from the Deals sheet so they can never drift out of sync.
B8: Stats sheet | C8: Aggregate views computed with formulas (COUNTIFS/SUMIFS/AVERAGEIFS) over the Terms and Deals sheets — this is the layer a 'stats dashboard' view would read from directly.
B9: Source Package | C9: Matches the zip file names delivered earlier, so each row can be traced back to the actual PDF and section it came from.
B10: Status | C10: This is illustrative/synthetic data for MVP purposes — all companies, people, and figures are fictional.

Sheet Deals
A1: Deal ID | B1: Company | C1: Deal Type | D1: Round / Stage | E1: Closing Date | F1: Vintage Year | G1: Lead Investor / Buyer | H1: Other Investors | I1: Investment Amount (USD) | J1: Valuation (USD) | K1: Valuation Basis | L1: Security Type | M1: Governing Law | N1: Source Package
A2: D1 | B2: Solara Robotics, Inc. | C2: SAFE | D2: Seed | E2: 2025-03-04 | F2: =YEAR(E2) -> 2025 | G2: Meridian Seed Fund I, L.P. | H2: — | I2: 250000 | J2: 8000000 | K2: Post-Money Valuation Cap | L2: SAFE (cap, no discount) | M2: Delaware | N2: 01_Solara Robotics - SAFE (Seed)
A3: D2 | B3: Northwind Analytics, Inc. | C3: SAFE | D3: Seed | E3: 2025-09-18 | F3: =YEAR(E3) -> 2025 | G3: Bay Harbor Angels, LLC | H3: — | I3: 150000 | K3: No Cap — Discount Only | L3: SAFE (discount, no cap) | M3: Delaware | N3: 02_Northwind Analytics - SAFE (Seed)
A4: D3 | B4: Cascadia Biotics, Inc. | C4: Priced Equity Round | D4: Seed | E4: 2026-01-12 | F4: =YEAR(E4) -> 2026 | G4: Ridgeline Capital Partners, L.P. | H4: Meridian Seed Fund I (SAFE conv.); Tributary Angel Syndicate; Founders Collective Seed Fund II | I4: 3000000 | J4: 12000000 | K4: Pre-Money | L4: Series Seed Preferred Stock | M4: Delaware | N4: 03_Cascadia Biotics - Seed Priced Round
A5: D4 | B5: Cascadia Biotics, Inc. | C5: Priced Equity Round | D5: Series A | E5: 2026-10-06 | F5: =YEAR(E5) -> 2026 | G5: Halcyon Growth Partners, L.P. | H5: Ridgeline Capital Partners (pro rata); Founders Collective Seed Fund II (pro rata); Alcove Life Sciences Fund II | I5: 12000000 | J5: 40000000 | K5: Pre-Money | L5: Series A Preferred Stock | M5: Delaware | N5: 04_Cascadia Biotics - Series A (Follow-On)
A6: D5 | B6: Vantage Robotics, Inc. | C6: Secondary Sale | D6: Growth (Series B basis) | E6: 2026-05-20 | F6: =YEAR(E6) -> 2026 | G6: Longbow Secondary Opportunities Fund, L.P. | H6: — (seller: Tomas Reyes, founder) | I6: 1800000 | J6: 95000000 | K6: Implied (last-round basis) | L6: Common Stock (secondary) | M6: Delaware | N6: 05_Vantage Robotics - Secondary Sale
A7: D6 | B7: Ferrum Health, Inc. | C7: M&A Exit | D7: Acquisition / Merger | E7: 2027-03-03 | F7: =YEAR(E7) -> 2027 | G7: Atlas MedTech Holdings, Inc. | H7: — (target stockholders: Series Seed, A, B + Common) | I7: 142000000 | J7: 142000000 | K7: Aggregate Merger Consideration | L7: Merger (cash + stock) | M7: Delaware | N7: 06_Ferrum Health - Exit (Merger with Atlas MedTech)

Sheet Terms
A1: Term ID | B1: Deal ID | C1: Company | D1: Deal Type | E1: Category | F1: Term | G1: Plain Language Summary | H1: Value | I1: Included (Y/N) | J1: Source Document | K1: Source Section
A2: T001 | B2: D1 | C2: =INDEX(Deals!$B$2:$B$7,MATCH(B2,Deals!$A$2:$A$7,0)) -> Solara Robotics, Inc. | D2: =INDEX(Deals!$C$2:$C$7,MATCH(B2,Deals!$A$2:$A$7,0)) -> SAFE | E2: Valuation / Price | F2: Valuation Cap | G2: Sets the maximum company value used to calculate the investor's conversion price in the next priced round. | H2: $8,000,000 (post-money) | I2: Y | J2: Solara Robotics - SAFE - Meridian Seed Fund I.pdf | K2: Cover page / §1.1
A3: T002 | B3: D1 | C3: =INDEX(Deals!$B$2:$B$7,MATCH(B3,Deals!$A$2:$A$7,0)) -> Solara Robotics, Inc. | D3: =INDEX(Deals!$C$2:$C$7,MATCH(B3,Deals!$A$2:$A$7,0)) -> SAFE | E3: Valuation / Price | F3: Discount Rate | G3: No discount applies — conversion price is driven solely by the valuation cap. | H3: None | I3: N | J3: Solara Robotics - SAFE - Meridian Seed Fund I.pdf | K3: Cover page
A4: T003 | B4: D1 | C4: =INDEX(Deals!$B$2:$B$7,MATCH(B4,Deals!$A$2:$A$7,0)) -> Solara Robotics, Inc. | D4: =INDEX(Deals!$C$2:$C$7,MATCH(B4,Deals!$A$2:$A$7,0)) -> SAFE | E4: Investor Protections | F4: Most Favored Nation | G4: No MFN clause — investor is not entitled to better terms offered to later SAFE holders. | H4: Not included | I4: N | J4: Solara Robotics - SAFE - Meridian Seed Fund I.pdf | K4: —
A5: T004 | B5: D1 | C5: =INDEX(Deals!$B$2:$B$7,MATCH(B5,Deals!$A$2:$A$7,0)) -> Solara Robotics, Inc. | D5: =INDEX(Deals!$C$2:$C$7,MATCH(B5,Deals!$A$2:$A$7,0)) -> SAFE | E5: Investor Protections | F5: Pro Rata Rights | G5: No side letter or pro rata right included with this instrument. | H5: Not included | I5: N | J5: Solara Robotics - SAFE - Meridian Seed Fund I.pdf | K5: —
A6: T005 | B6: D1 | C6: =INDEX(Deals!$B$2:$B$7,MATCH(B6,Deals!$A$2:$A$7,0)) -> Solara Robotics, Inc. | D6: =INDEX(Deals!$C$2:$C$7,MATCH(B6,Deals!$A$2:$A$7,0)) -> SAFE | E6: Liquidity | F6: Liquidity Event Treatment | G6: On a change of control or IPO, investor gets the greater of their money back or the as-converted value. | H6: Cash-out vs. conversion amount, greater of | I6: Y | J6: Solara Robotics - SAFE - Meridian Seed Fund I.pdf | K6: §1.2
A7: T006 | B7: D1 | C7: =INDEX(Deals!$B$2:$B$7,MATCH(B7,Deals!$A$2:$A$7,0)) -> Solara Robotics, Inc. | D7: =INDEX(Deals!$C$2:$C$7,MATCH(B7,Deals!$A$2:$A$7,0)) -> SAFE | E7: Governance | F7: Governing Law | G7: Delaware law governs the instrument. | H7: Delaware | I7: Y | J7: Solara Robotics - SAFE - Meridian Seed Fund I.pdf | K7: §5
A8: T007 | B8: D2 | C8: =INDEX(Deals!$B$2:$B$7,MATCH(B8,Deals!$A$2:$A$7,0)) -> Northwind Analytics, Inc. | D8: =INDEX(Deals!$C$2:$C$7,MATCH(B8,Deals!$A$2:$A$7,0)) -> SAFE | E8: Valuation / Price | F8: Valuation Cap | G8: No cap — conversion price is set only by applying the discount to the next round's price. | H8: None | I8: N | J8: Northwind Analytics - SAFE - Bay Harbor Angels.pdf | K8: Cover page
A9: T008 | B9: D2 | C9: =INDEX(Deals!$B$2:$B$7,MATCH(B9,Deals!$A$2:$A$7,0)) -> Northwind Analytics, Inc. | D9: =INDEX(Deals!$C$2:$C$7,MATCH(B9,Deals!$A$2:$A$7,0)) -> SAFE | E9: Valuation / Price | F9: Discount Rate | G9: Investor converts at a 20% discount to the price paid by new investors in the next priced round. | H9: 20% discount (80% of round price) | I9: Y | J9: Northwind Analytics - SAFE - Bay Harbor Angels.pdf | K9: Cover page / §1.1
A10: T009 | B10: D2 | C10: =INDEX(Deals!$B$2:$B$7,MATCH(B10,Deals!$A$2:$A$7,0)) -> Northwind Analytics, Inc. | D10: =INDEX(Deals!$C$2:$C$7,MATCH(B10,Deals!$A$2:$A$7,0)) -> SAFE | E10: Investor Protections | F10: Most Favored Nation | G10: If the company later issues a SAFE on better terms, investor can elect to swap in those terms. | H10: Included, 15-day election window | I10: Y | J10: Northwind Analytics - Side Letter - MFN and Pro Rata.pdf | K10: §1
A11: T010 | B11: D2 | C11: =INDEX(Deals!$B$2:$B$7,MATCH(B11,Deals!$A$2:$A$7,0)) -> Northwind Analytics, Inc. | D11: =INDEX(Deals!$C$2:$C$7,MATCH(B11,Deals!$A$2:$A$7,0)) -> SAFE | E11: Investor Protections | F11: Pro Rata Rights | G11: Investor can participate in a future priced round to maintain their ownership percentage. | H11: Included, 10-business-day notice | I11: Y | J11: Northwind Analytics - Side Letter - MFN and Pro Rata.pdf | K11: §2
A12: T011 | B12: D2 | C12: =INDEX(Deals!$B$2:$B$7,MATCH(B12,Deals!$A$2:$A$7,0)) -> Northwind Analytics, Inc. | D12: =INDEX(Deals!$C$2:$C$7,MATCH(B12,Deals!$A$2:$A$7,0)) -> SAFE | E12: Investor Protections | F12: Information Rights | G12: Investor receives annual and quarterly unaudited financials. | H12: Annual (90 days) + quarterly (45 days) | I12: Y | J12: Northwind Analytics - Side Letter - MFN and Pro Rata.pdf | K12: §3
A13: T012 | B13: D2 | C13: =INDEX(Deals!$B$2:$B$7,MATCH(B13,Deals!$A$2:$A$7,0)) -> Northwind Analytics, Inc. | D13: =INDEX(Deals!$C$2:$C$7,MATCH(B13,Deals!$A$2:$A$7,0)) -> SAFE | E13: Liquidity | F13: Liquidity Event Treatment | G13: Investor can elect cash-out or as-converted common stock treatment on a liquidity event. | H13: Cash-out, with common-stock election | I13: Y | J13: Northwind Analytics - SAFE - Bay Harbor Angels.pdf | K13: §1.2
... A46: T045 | B46: D6 | C46: =INDEX(Deals!$B$2:$B$7,MATCH(B46,Deals!$A$2:$A$7,0)) -> Ferrum Health, Inc. | D46: =INDEX(Deals!$C$2:$C$7,MATCH(B46,Deals!$A$2:$A$7,0)) -> M&A Exit | E46: Compliance | F46: Closing Conditions | G46: Key conditions that must be satisfied before the deal can close. | H46: Majority + per-series stockholder vote; HSR clearance; 90% signed Letters of Transmittal | I46: Y | J46: 1 - Agreement and Plan of Merger.pdf | K46: §4

Sheet Stats
B2: Deal Stats (computed live from Deals + Terms)
B3: All figures below are formulas — they recompute automatically if rows are added to Deals or Terms.
B5: Deals by Type
B6: Deal Type | C6: Count | D6: Total Investment (USD)
B7: SAFE | C7: =COUNTIF(Deals!$C$2:$C$7,B7) -> 2 | D7: =SUMIF(Deals!$C$2:$C$7,B7,Deals!$I$2:$I$7) -> 400000
B8: Priced Equity Round | C8: =COUNTIF(Deals!$C$2:$C$7,B8) -> 2 | D8: =SUMIF(Deals!$C$2:$C$7,B8,Deals!$I$2:$I$7) -> 15000000
B9: Secondary Sale | C9: =COUNTIF(Deals!$C$2:$C$7,B9) -> 1 | D9: =SUMIF(Deals!$C$2:$C$7,B9,Deals!$I$2:$I$7) -> 1800000
B10: M&A Exit | C10: =COUNTIF(Deals!$C$2:$C$7,B10) -> 1 | D10: =SUMIF(Deals!$C$2:$C$7,B10,Deals!$I$2:$I$7) -> 142000000
B11: Total | C11: =SUM(C7:C10) -> 6 | D11: =SUM(D7:D10) -> 159200000
B14: SAFE Structure Comparison
B15: Metric | C15: Value
B16: SAFEs with a Valuation Cap | C16: =COUNTIFS(Deals!$C$2:$C$7,"SAFE",Deals!$J$2:$J$7,">0") -> 1
B17: SAFEs with Discount Only (no cap) | C17: =COUNTIFS(Deals!$C$2:$C$7,"SAFE",Deals!$K$2:$K$7,"No Cap — Discount Only") -> 1
B18: Average Valuation Cap (where present) | C18: =AVERAGEIFS(Deals!$J$2:$J$7,Deals!$C$2:$C$7,"SAFE",Deals!$J$2:$J$7,">0") -> 8000000
B21: Term Frequency by Category (Included = Y)
B22: Category | C22: # Terms Tagged | D22: # Included (Y)
B23: Valuation / Price | C23: =COUNTIF(Terms!$E$2:$E$46,B23) -> 11 | D23: =COUNTIFS(Terms!$E$2:$E$46,B23,Terms!$I$2:$I$46,"Y") -> 9
B24: Economics | C24: =COUNTIF(Terms!$E$2:$E$46,B24) -> 5 | D24: =COUNTIFS(Terms!$E$2:$E$46,B24,Terms!$I$2:$I$46,"Y") -> 5
B25: Governance | C25: =COUNTIF(Terms!$E$2:$E$46,B25) -> 7 | D25: =COUNTIFS(Terms!$E$2:$E$46,B25,Terms!$I$2:$I$46,"Y") -> 7
B26: Investor Protections | C26: =COUNTIF(Terms!$E$2:$E$46,B26) -> 12 | D26: =COUNTIFS(Terms!$E$2:$E$46,B26,Terms!$I$2:$I$46,"Y") -> 10
B27: Liquidity | C27: =COUNTIF(Terms!$E$2:$E$46,B27) -> 2 | D27: =COUNTIFS(Terms!$E$2:$E$46,B27,Terms!$I$2:$I$46,"Y") -> 2
B28: Mechanics | C28: =COUNTIF(Terms!$E$2:$E$46,B28) -> 3 | D28: =COUNTIFS(Terms!$E$2:$E$46,B28,Terms!$I$2:$I$46,"Y") -> 3
B29: Risk Allocation | C29: =COUNTIF(Terms!$E$2:$E$46,B29) -> 2 | D29: =COUNTIFS(Terms!$E$2:$E$46,B29,Terms!$I$2:$I$46,"Y") -> 2
B30: Compliance | C30: =COUNTIF(Terms!$E$2:$E$46,B30) -> 2 | D30: =COUNTIFS(Terms!$E$2:$E$46,B30,Terms!$I$2:$I$46,"Y") -> 2
B31: Conversion | C31: =COUNTIF(Terms!$E$2:$E$46,B31) -> 1 | D31: =COUNTIFS(Terms!$E$2:$E$46,B31,Terms!$I$2:$I$46,"Y") -> 1
B34: Named Clause Frequency (across all 6 deals)
B35: Clause | C35: # Deals Included | D35: % of Deals
B36: Most Favored Nation | C36: =COUNTIFS(Terms!$F$2:$F$46,B36,Terms!$I$2:$I$46,"Y") -> 1 | D36: =C36/6 -> 0.16666667
B37: Pro Rata Rights | C37: =COUNTIFS(Terms!$F$2:$F$46,B37,Terms!$I$2:$I$46,"Y") -> 1 | D37: =C37/6 -> 0.16666667
B38: Registration Rights | C38: =COUNTIFS(Terms!$F$2:$F$46,B38,Terms!$I$2:$I$46,"Y") -> 1 | D38: =C38/6 -> 0.16666667
B39: Drag-Along Right | C39: =COUNTIFS(Terms!$F$2:$F$46,B39,Terms!$I$2:$I$46,"Y") -> 1 | D39: =C39/6 -> 0.16666667
B40: Right of First Refusal & Co-Sale | C40: =COUNTIFS(Terms!$F$2:$F$46,B40,Terms!$I$2:$I$46,"Y") -> 1 | D40: =C40/6 -> 0.16666667
B41: Anti-Dilution | C41: =COUNTIFS(Terms!$F$2:$F$46,B41,Terms!$I$2:$I$46,"Y") -> 1 | D41: =C41/6 -> 0.16666667
B42: Information Rights | C42: =COUNTIFS(Terms!$F$2:$F$46,B42,Terms!$I$2:$I$46,"Y") -> 2 | D42: =C42/6 -> 0.33333333

Sheet Dicionario_Termos
B2: Dicionário de Termos — MVP
B3: Termos únicos consolidados a partir dos 6 deals mockup, com exemplos reais de redação e sinônimos conhecidos. Usado pelo agente de extração para reconhecer cada termo mesmo com fraseado diferente.
A5: ID | B5: Categoria | C5: Termo Canônico | D5: Definição (linguagem simples) | E5: Sinônimos / Também aparece como | F5: Exemplo de Redação #1 | G5: Fonte do Exemplo #1 | H5: Exemplo de Redação #2 (variação) | I5: Fonte do Exemplo #2
A6: DT001 | B6: Valuation / Price | C6: Valuation Cap | D6: Teto de valuation usado para calcular o preço de conversão do investidor na próxima rodada precificada. | E6: Post-Money Valuation Cap; Cap | F6: “...calculated using the Post-Money Valuation Cap of $8,000,000.00.” | G6: SAFE — Solara Robotics | H6: Ausente no instrumento (cover page indica ‘None’) quando a estrutura é só desconto. | I6: SAFE — Northwind Analytics
A7: DT002 | B7: Valuation / Price | C7: Discount Rate | D7: Percentual de desconto aplicado ao preço por ação da próxima rodada, para o investidor converter mais barato. | E7: Discount Price; Desconto | F7: “this Safe will automatically convert into the number of shares... equal to the Purchase Amount divided by the Discount Price.” | G7: SAFE — Northwind Analytics | H7: “Discount Rate: None” (quando a estrutura usa cap em vez de desconto) | I7: SAFE — Solara Robotics
A8: DT003 | B8: Valuation / Price | C8: Price Per Share | D8: Preço pago por ação na rodada, usado para calcular quanto cada investidor recebe de participação. | E8: Purchase Price per Share; Original Issue Price | F8: “at a purchase price of $1.4278 per share.” | G8: Series Seed Stock Purchase Agreement — Cascadia Biotics | H8: “at a purchase price of $4.9016 per share.” | I8: Series A Stock Purchase Agreement — Cascadia Biotics
A9: DT004 | B9: Valuation / Price | C9: Pre-Money Valuation | D9: Valor atribuído à empresa imediatamente antes do novo investimento entrar. | E9: Pre-Money; valuation pré-investimento | F9: “Pre-Money Valuation: $12,000,000.00” | G9: Series Seed Stock Purchase Agreement — Cascadia Biotics | H9: “Pre-Money Valuation: $40,000,000.00” | I9: Series A Stock Purchase Agreement — Cascadia Biotics
A10: DT005 | B10: Valuation / Price | C10: Implied Company Valuation | D10: Valuation da empresa inferido a partir do preço pago numa transação secundária, com base na última rodada precificada. | E10: Implied Valuation (secondary basis) | F10: “Company Valuation (Implied): $95,000,000.00 (based on most recent Series B price)” | G10: Secondary Stock Purchase Agreement — Vantage Robotics | H10: — | I10: —
A11: DT006 | B11: Economics | C11: Liquidation Preference | D11: Define quem recebe dinheiro primeiro (e quanto) numa venda ou liquidação, antes dos demais acionistas. | E11: Liq Pref; Preferência de liquidação | F11: “the holders of Series Seed Preferred Stock shall be entitled to receive... an amount per share equal to one times (1x) the Original Issue Price.” | G11: Certificate of Incorporation — Cascadia Biotics (Seed) | H11: “The Series A Preferred Stock ranks senior to the Series Seed Preferred Stock and the Common Stock with respect to distributions upon a Liquidation Event.” | I11: Certificate of Incorporation — Cascadia Biotics (Series A)
A12: DT007 | B12: Economics | C12: Liquidation Waterfall | D12: A ordem e os valores em que diferentes classes de ações são pagas numa saída, do mais sênior ao residual. | E12: Payment Spreadsheet; ordem de preferência | F12: “the Series B Preferred Stock shall receive its 1x liquidation preference of $52,000,000 in the aggregate, the Series A Preferred Stock shall receive its 1x liquidation preference of $28,000,000...” | G12: Agreement and Plan of Merger — Ferrum Health | H12: — | I12: —
A13: DT008 | B13: Economics | C13: Dividend Rate | D13: Percentual de dividendo preferencial que os investidores podem receber se o board declarar dividendos. | E13: Dividend Preference | F13: “the holders of Series Seed Preferred Stock shall be entitled to receive dividends... at the rate of 8% of the Original Issue Price per annum, non-cumulative.” | G13: Certificate of Incorporation — Cascadia Biotics (Seed) | H13: — | I13: —
A14: DT009 | B14: Economics | C14: Anti-Dilution | D14: Mecanismo que protege o investidor de diluição excessiva caso a empresa levante uma rodada futura a preço mais baixo. | E14: Anti-Dilution Adjustment; Down-Round Protection | F14: “subject to customary anti-dilution adjustments on a broad-based weighted average basis.” | G14: Certificate of Incorporation — Cascadia Biotics (Series A) | H14: — | I14: —
A15: DT010 | B15: Governance | C15: Board Composition | D15: Como os assentos do conselho são divididos entre fundadores, investidores e membros independentes. | E15: Board Seats; Composição do Board | F15: “One (1) member designated by Ridgeline Capital Partners, L.P., so long as it holds at least 500,000 shares of Series Seed Preferred Stock.” | G15: Voting Agreement — Cascadia Biotics (Seed) | H15: “Two (2) members designated by Halcyon Growth Partners, L.P., so long as it holds at least 1,000,000 shares of Series A Preferred Stock.” | I15: Amended and Restated Voting Agreement — Cascadia Biotics (Series A)
A16: DT011 | B16: Governance | C16: Protective Provisions | D16: Lista de ações da empresa que exigem aprovação dos investidores preferenciais, além do board. | E16: Consentimento de Preferred; Veto Rights | F16: “the Corporation shall not, without the affirmative vote... of the holders of a majority of the outstanding Series Seed Preferred Stock: (a) amend the Certificate... (b) authorize or issue any new class or series of stock with rights senior to or on parity...” | G16: Certificate of Incorporation — Cascadia Biotics (Seed) | H16: — | I16: —
... A34: DT029 | B34: Governance | C34: Governing Law | D34: A jurisdição cujas leis regem a interpretação e execução do contrato. | E34: Choice of Law | F34: “This Safe... will be governed by and construed under the laws of the State of Delaware.” | G34: SAFE — Solara Robotics | H34: — | I34: —
